[{"hospName":"목동병원","itemName":"치료재료/유방 생검용/ATEC(PROBE & VACCUM SET)","price":725000,"ediCode":"BM0001MT","date":"2025-09-03","unit":"-","category":"-"},{"hospName":"목동병원","itemName":"초음파검사료(진단초음파)/근골격, 연부-관절 초음파/발목관절","price":84000,"ediCode":"EB4680000","date":"2025-09-03","unit":"-","category":"-"},{"hospName":"목동병원","itemName":"초음파검사료(진단초음파)/흉부-흉벽,흉막,늑골 등 초음파","price":211000,"ediCode":"EB4220000","date":"2025-09-03","unit":"-","category":"-"},{"hospName":"목동병원","itemName":"제증명수수료/확인서/통원","price":3000,"ediCode":"PDZ090004","date":"2025-09-03","unit":"-","category":"-"},{"hospName":"목동병원","itemName":"이학요법료/언어치료","price":77000,"ediCode":"MZ0060000","date":"2025-09-03","unit":"-","category":"-"},{"hospName":"목동병원","itemName":"치과의 보철료/크라운/올세라믹","price":521000,"ediCode":"UW609F340","date":"2025-09-03","unit":"-","category":"-"},{"hospName":"목동병원","itemName":"기능 검사료(신경계 기능검사)/정량적감각기능검사/진동역치","price":30600,"ediCode":"FY8810000","date":"2025-09-03","unit":"-","category":"-"},{"hospName":"목동병원","itemName":"이학요법료/언어치료","price":54700,"ediCode":"MZ0060000","date":"2025-09-03","unit":"-","category":"-"},{"hospName":"목동병원","itemName":"기능 검사료(신경계 기능검사)/초음파를 활용한 뇌혈류 기능검사","price":130000,"ediCode":"FZ7140000","date":"2025-09-03","unit":"-","category":"-"},{"hospName":"목동병원","itemName":"초음파검사료(기본초음파)/단순초음파/Ⅱ","price":87000,"ediCode":"EB4020000","date":"2025-09-03","unit":"-","category":"-"},{"hospName":"목동병원","itemName":"초음파 검사료(유도 초음파)/유도초음파/Ⅳ","price":515000,"ediCode":"EB5640000","date":"2025-09-03","unit":"-","category":"-"},{"hospName":"목동병원","itemName":"치료재료/재조합골형성단백질(RHBMP-2) 함유 골이식재/NOVOSIS DENT","price":362500,"ediCode":"BC0301KJ","date":"2025-10-27","unit":"-","category":"-"},{"hospName":"목동병원","itemName":"초음파검사료(진단초음파)/복부-여성생식기 초음파/정밀","price":294000,"ediCode":"EB4570001","date":"2025-09-03","unit":"-","category":"-"},{"hospName":"목동병원","itemName":"기능 검사료(평형 및 청각 기능검사)/회전검사","price":21800,"ediCode":"FZ7320000","date":"2025-09-03","unit":"-","category":"-"},{"hospName":"목동병원","itemName":"초음파 검사료(유도 초음파)/유도초음파/Ⅰ","price":211000,"ediCode":"EB5610000","date":"2025-09-03","unit":"-","category":"-"},{"hospName":"목동병원","itemName":"자기공명영상진단료(MRI-기본검사)/복부-간/일반","price":822000,"ediCode":"HE1320001","date":"2025-09-03","unit":"-","category":"-"},{"hospName":"목동병원","itemName":"치료재료/동종진피(IMPLANT용-유방재건술용 제외)/MEGADERM","price":37400,"ediCode":"BTS01019","date":"2025-09-03","unit":"-","category":"-"},{"hospName":"목동병원","itemName":"기능 검사료(시기능검사)/안구광학단층촬영","price":76100,"ediCode":"EZ7960000","date":"2025-09-03","unit":"-","category":"-"},{"hospName":"목동병원","itemName":"초음파 검사료(유도 초음파)/유도초음파/Ⅱ","price":275000,"ediCode":"EB5620000","date":"2025-09-03","unit":"-","category":"-"},{"hospName":"목동병원","itemName":"처치 및 수술료(신경)/내시경적 경막외강 신경근성형술","price":1000000,"ediCode":"SZ6310000","date":"2025-09-03","unit":"-","category":"-"},{"hospName":"목동병원","itemName":"기능 검사료(신경계 기능검사)/수면리듬양상검사","price":18800,"ediCode":"FZ7000000","date":"2025-09-03","unit":"-","category":"-"},{"hospName":"목동병원","itemName":"주사료/알레르겐 면역요법","price":540000,"ediCode":"KZ0010000","date":"2025-09-03","unit":"-","category":"-"},{"hospName":"목동병원","itemName":"치과의 보철료/크라운/Zirconia","price":521000,"ediCode":"UW609F350","date":"2025-09-03","unit":"-","category":"-"},{"hospName":"목동병원","itemName":"초음파 검사료(유도 초음파)/수술 중 초음파","price":515000,"ediCode":"EZ9850000","date":"2025-09-03","unit":"-","category":"-"},{"hospName":"목동병원","itemName":"초음파검사료(진단초음파)/근골격, 연부-관절 초음파/발목관절","price":84000,"ediCode":"EB4680000","date":"2025-09-03","unit":"-","category":"-"},{"hospName":"목동병원","itemName":"초음파 검사료(유도 초음파)/유도초음파/Ⅰ","price":316000,"ediCode":"EB5610000","date":"2025-09-03","unit":"-","category":"-"},{"hospName":"목동병원","itemName":"초음파검사료(진단초음파)/복부-복부 초음파/간·담낭·담도·비장·췌장-일반","price":203000,"ediCode":"EB4410000","date":"2025-09-03","unit":"-","category":"-"},{"hospName":"목동병원","itemName":"기능 검사료(신경계 기능검사)/자율신경계이상검사/기립성혈압검사","price":52500,"ediCode":"FY8910000","date":"2025-09-03","unit":"-","category":"-"},{"hospName":"목동병원","itemName":"기능 검사료(알레르기 검사)/경구 음식물유발시험과 경구 약물유발시험검사","price":154100,"ediCode":"EZ8480000","date":"2025-09-03","unit":"-","category":"-"},{"hospName":"목동병원","itemName":"예방접종료/B형간염/유박스비주 0.5mL","price":22000,"ediCode":"3Z5202106","date":"2025-09-03","unit":"-","category":"-"},{"hospName":"목동병원","itemName":"초음파 검사료(특수 초음파)/심장-경식도 심초음파","price":1005000,"ediCode":"EB6110000","date":"2025-09-03","unit":"-","category":"-"},{"hospName":"목동병원","itemName":"처치 및 수술료(기타)/로봇 보조 수술 [시술시 소요재료 포함]-다빈치 기기/갑상선악성종양근치수술(갑상선암)","price":14000000,"ediCode":"QZ9610002","date":"2025-09-03","unit":"-","category":"-"},{"hospName":"목동병원","itemName":"기능 검사료(순환기 기능 검사)/관상동맥내 광학파 단층촬영","price":266500,"ediCode":"EZ8710000","date":"2025-09-03","unit":"-","category":"-"},{"hospName":"목동병원","itemName":"초음파검사료(기본초음파)/단순초음파/Ⅱ","price":61000,"ediCode":"EB4020000","date":"2025-09-03","unit":"-","category":"-"},{"hospName":"목동병원","itemName":"예방접종료/홍역/유행성이하선염/풍진/엠엠알II","price":30400,"ediCode":"3Z5201901","date":"2025-09-03","unit":"-","category":"-"},{"hospName":"목동병원","itemName":"초음파검사료(진단초음파)/심장-경흉부 심초음파/일반","price":342000,"ediCode":"EB4320000","date":"2025-09-03","unit":"-","category":"-"},{"hospName":"목동병원","itemName":"초음파검사료(진단초음파)/혈관-사지혈관 도플러 초음파/하지-정맥","price":164000,"ediCode":"EB4880000","date":"2025-09-03","unit":"-","category":"-"},{"hospName":"목동병원","itemName":"초음파 검사료(특수 초음파)/기관지내시경초음파 [가이드시스를 이용한 경우 포함]/기관지내시경초음파","price":786000,"ediCode":"EZ9910001","date":"2025-09-03","unit":"-","category":"-"},{"hospName":"목동병원","itemName":"자기공명영상진단료(MRI-기본검사)/근골격계-주관절/일반","price":786000,"ediCode":"HE1160000","date":"2025-09-03","unit":"-","category":"-"},{"hospName":"목동병원","itemName":"예방접종료/사람유두종바이러스 감염증(HPV 백신)/가다실 프리필드시린지","price":180000,"ediCode":"3Z5201002","date":"2025-09-03","unit":"-","category":"-"},{"hospName":"목동병원","itemName":"초음파검사료(진단초음파)/근골격, 연부-관절 초음파/주관절","price":105000,"ediCode":"EB4630000","date":"2025-09-03","unit":"-","category":"-"},{"hospName":"목동병원","itemName":"기능 검사료(시기능검사)/눈의 계측검사[편측]/레이저 간섭계 이용","price":121400,"ediCode":"E78010000","date":"2025-09-03","unit":"-","category":"-"},{"hospName":"목동병원","itemName":"처치 및 수술료(신경)/경피적 경막외강 신경성형술","price":500000,"ediCode":"SZ6340000","date":"2025-09-03","unit":"-","category":"-"},{"hospName":"목동병원","itemName":"치료재료/조절성 인공수정체/PRECIZON TORIC 565","price":1232000,"ediCode":"BI0201YX","date":"2025-09-03","unit":"-","category":"-"},{"hospName":"목동병원","itemName":"내시경, 천자 및 생검료 /진정내시경환자관리료 /Ⅲ","price":139000,"ediCode":"EA0030000","date":"2025-09-03","unit":"-","category":"-"},{"hospName":"목동병원","itemName":"기능 검사료(순환기 기능 검사)/동맥경화도검사(맥파전달속도측정)","price":49200,"ediCode":"EZ8680000","date":"2025-09-03","unit":"-","category":"-"},{"hospName":"목동병원","itemName":"제증명수수료/영문진단서/일반","price":20000,"ediCode":"PDE010001","date":"2025-09-03","unit":"-","category":"-"},{"hospName":"목동병원","itemName":"치료재료/조절성 인공수정체/테크니스 퓨어SEE 토릭","price":1987700,"ediCode":"BI0213LN","date":"2025-09-03","unit":"-","category":"-"},{"hospName":"목동병원","itemName":"기능 검사료(신경계 기능검사)/언어전반진단검사","price":66000,"ediCode":"FZ6890000","date":"2025-09-03","unit":"-","category":"-"},{"hospName":"목동병원","itemName":"기능 검사료(신경계 기능검사)/발음 및 발성검사","price":9900,"ediCode":"FZ6880000","date":"2025-09-03","unit":"-","category":"-"},{"hospName":"목동병원","itemName":"제증명수수료/시체검안서","price":30000,"ediCode":"PDZ040000","date":"2025-09-03","unit":"-","category":"-"},{"hospName":"목동병원","itemName":"초음파검사료(진단초음파)/혈관-두개외 혈관 도플러 초음파/경동맥","price":295000,"ediCode":"EB4820000","date":"2025-09-03","unit":"-","category":"-"},{"hospName":"목동병원","itemName":"초음파 검사료(유도 초음파)/유도초음파/Ⅰ","price":103000,"ediCode":"EB5610000","date":"2025-09-03","unit":"-","category":"-"},{"hospName":"목동병원","itemName":"초음파검사료(진단초음파)/임산부 초음파/제2,3삼분기 -정밀","price":250000,"ediCode":"EB5170000","date":"2025-09-03","unit":"-","category":"-"},{"hospName":"목동병원","itemName":"예방접종료/Tdap(파상풍, 디프테리아, 백일해)/아다셀주","price":40000,"ediCode":"3Z5201602","date":"2025-09-03","unit":"-","category":"-"},{"hospName":"목동병원","itemName":"기능 검사료(신경계 기능검사)/주의력검사","price":52400,"ediCode":"FZ6900000","date":"2025-09-03","unit":"-","category":"-"},{"hospName":"목동병원","itemName":"초음파 검사료(유도 초음파)/유도초음파/Ⅲ","price":112000,"ediCode":"EB5630000","date":"2025-09-03","unit":"-","category":"-"},{"hospName":"목동병원","itemName":"기능 검사료(시기능검사)/눈의 계측검사[편측]/초음파 이용","price":83700,"ediCode":"E78000000","date":"2025-09-03","unit":"-","category":"-"},{"hospName":"목동병원","itemName":"기능 검사료(신경계 기능검사)/발음 및 발성검사","price":29000,"ediCode":"FZ6880000","date":"2025-09-03","unit":"-","category":"-"},{"hospName":"목동병원","itemName":"자기공명영상진단료(MRI-특수검사)/관류 [3차원자기공명영상 포함]","price":491000,"ediCode":"HF1020000","date":"2025-09-03","unit":"-","category":"-"},{"hospName":"목동병원","itemName":"기능 검사료 (치아검사)/인상채득 및 모형제작 [1악당]","price":18000,"ediCode":"EX9340000","date":"2025-09-03","unit":"-","category":"-"},{"hospName":"목동병원","itemName":"치료재료/동종진피(IMPLANT용-유방재건술용 제외)/CGDERM MATRIX - IMPLANT","price":51000,"ediCode":"BTS01313","date":"2025-10-22","unit":"-","category":"-"},{"hospName":"목동병원","itemName":"기능 검사료(알레르기 검사)/경구 음식물유발시험과 경구 약물유발시험검사","price":54700,"ediCode":"EZ8480000","date":"2025-09-03","unit":"-","category":"-"},{"hospName":"목동병원","itemName":"제증명수수료/진료기록사본/6매 이상","price":100,"ediCode":"PDZ110102","date":"2025-09-03","unit":"-","category":"-"},{"hospName":"목동병원","itemName":"초음파검사료(기본초음파)/단순초음파/Ⅱ","price":133000,"ediCode":"EB4020000","date":"2025-09-03","unit":"-","category":"-"},{"hospName":"목동병원","itemName":"기능 검사료(신경계 기능검사)/언어전반진단검사","price":229000,"ediCode":"FZ6890000","date":"2025-09-03","unit":"-","category":"-"},{"hospName":"목동병원","itemName":"초음파검사료(진단초음파)/근골격, 연부-관절 초음파/고관절","price":105000,"ediCode":"EB4650000","date":"2025-09-03","unit":"-","category":"-"},{"hospName":"목동병원","itemName":"치료재료/관상동맥내 광학파 단층촬영용/DRAGONFLY OPSTAR IMAGING CATHETER","price":2210000,"ediCode":"BJ4514LR","date":"2025-09-03","unit":"-","category":"-"},{"hospName":"목동병원","itemName":"초음파검사료(진단초음파)/임산부 초음파/제1삼분기 -정밀","price":137000,"ediCode":"EB5130000","date":"2025-09-03","unit":"-","category":"-"},{"hospName":"목동병원","itemName":"자기공명영상진단료(MRI-기본검사)/근골격계-견관절/조영제 주입 전·후 촬영 판독","price":819000,"ediCode":"HE2150000","date":"2025-09-03","unit":"-","category":"-"},{"hospName":"목동병원","itemName":"치과 처치· 수술료/광중합형 복합레진 충전/우식-2면","price":160000,"ediCode":"U02400000","date":"2025-09-03","unit":"-","category":"-"},{"hospName":"목동병원","itemName":"초음파검사료(진단초음파)/근골격, 연부-관절 초음파/손목관절","price":84000,"ediCode":"EB4670000","date":"2025-09-03","unit":"-","category":"-"},{"hospName":"목동병원","itemName":"초음파검사료(기본초음파)/단순초음파/Ⅱ","price":63000,"ediCode":"EB4020000","date":"2025-09-03","unit":"-","category":"-"},{"hospName":"목동병원","itemName":"자기공명영상진단료(MRI-기본검사)/근골격계-주관절/조영제 주입 전·후 촬영 판독","price":819000,"ediCode":"HE2160000","date":"2025-09-03","unit":"-","category":"-"},{"hospName":"목동병원","itemName":"초음파검사료(진단초음파)/혈관-사지혈관 도플러 초음파/하지-동맥","price":216000,"ediCode":"EB4870000","date":"2025-09-03","unit":"-","category":"-"},{"hospName":"목동병원","itemName":"치료재료/척추경막외 유착방지제/MEDICLORE","price":174000,"ediCode":"BM2101QT","date":"2025-09-03","unit":"-","category":"-"},{"hospName":"목동병원","itemName":"초음파 검사료(유도 초음파)/유도초음파/Ⅱ","price":265000,"ediCode":"EB5620000","date":"2025-09-03","unit":"-","category":"-"},{"hospName":"목동병원","itemName":"치료재료/척추경막외 유착방지제/ARTQ, COVER SEAL","price":188500,"ediCode":"BF0100AJ","date":"2025-09-03","unit":"-","category":"-"},{"hospName":"목동병원","itemName":"제증명수수료/상해진단서/3주 미만","price":100000,"ediCode":"PDZ020001","date":"2025-09-03","unit":"-","category":"-"},{"hospName":"목동병원","itemName":"초음파검사료(진단초음파)/두경부-경부 초음파/갑상선·부갑상선","price":191000,"ediCode":"EB4140000","date":"2025-09-03","unit":"-","category":"-"},{"hospName":"목동병원","itemName":"초음파검사료(진단초음파)/혈관-뇌혈류 초음파","price":229000,"ediCode":"EB4810000","date":"2025-09-03","unit":"-","category":"-"},{"hospName":"목동병원","itemName":"초음파검사료(진단초음파)/복부-남성생식기 초음파/전립선·정낭","price":183000,"ediCode":"EB4510001","date":"2025-09-03","unit":"-","category":"-"},{"hospName":"목동병원","itemName":"초음파검사료(진단초음파)/복부-남성생식기 초음파/음낭","price":295000,"ediCode":"EB4540001","date":"2025-09-03","unit":"-","category":"-"},{"hospName":"목동병원","itemName":"초음파검사료(진단초음파)/심장-경흉부 심초음파/일반","price":293000,"ediCode":"EB4320000","date":"2025-09-03","unit":"-","category":"-"},{"hospName":"목동병원","itemName":"치료재료/척추경막외 유착방지제/INTERBLOCK, GUARDIANWRAP PLUS","price":638000,"ediCode":"BF0100VD","date":"2025-10-27","unit":"-","category":"-"},{"hospName":"목동병원","itemName":"초음파 검사료(유도 초음파)/유도초음파/Ⅱ","price":265000,"ediCode":"EB5620000","date":"2025-09-03","unit":"-","category":"-"},{"hospName":"목동병원","itemName":"초음파 검사료(유도 초음파)/유도초음파/Ⅱ","price":202000,"ediCode":"EB5620000","date":"2025-09-03","unit":"-","category":"-"},{"hospName":"목동병원","itemName":"제증명수수료/사망진단서","price":10000,"ediCode":"PDZ030000","date":"2025-09-03","unit":"-","category":"-"},{"hospName":"목동병원","itemName":"이학요법료/신장분사치료","price":10900,"ediCode":"MZ0070000","date":"2025-09-03","unit":"-","category":"-"},{"hospName":"목동병원","itemName":"내시경, 천자 및 생검료 /진정내시경환자관리료 /Ⅰ","price":114000,"ediCode":"EA0010000","date":"2025-09-03","unit":"-","category":"-"},{"hospName":"목동병원","itemName":"초음파 검사료(특수 초음파)/혈관내초음파","price":200000,"ediCode":"EZ9940000","date":"2025-10-27","unit":"-","category":"-"},{"hospName":"목동병원","itemName":"초음파검사료(진단초음파)/혈관-사지혈관 도플러 초음파/하지-정맥","price":164000,"ediCode":"EB4880000","date":"2025-09-03","unit":"-","category":"-"},{"hospName":"목동병원","itemName":"예방접종료/인플루엔자(독감)/보령플루Ⅷ테트라백신주","price":40000,"ediCode":"3Z5201112","date":"2025-09-03","unit":"-","category":"-"},{"hospName":"목동병원","itemName":"초음파검사료(진단초음파)/근골격, 연부-관절 초음파/발목관절","price":105000,"ediCode":"EB4680000","date":"2025-09-03","unit":"-","category":"-"},{"hospName":"목동병원","itemName":"초음파검사료(진단초음파)/근골격, 연부-관절 초음파/슬관절","price":84000,"ediCode":"EB4640000","date":"2025-09-03","unit":"-","category":"-"},{"hospName":"목동병원","itemName":"검체검사료/성호르몬결합글로불린","price":70000,"ediCode":"CZ2020000","date":"2025-09-03","unit":"-","category":"-"},{"hospName":"목동병원","itemName":"자기공명영상진단료(MRI-기본검사)/두경부-안와/일반","price":786000,"ediCode":"HE1050001","date":"2025-09-03","unit":"-","category":"-"},{"hospName":"목동병원","itemName":"자기공명영상진단료(MRI-기본검사)/복부-음낭 및 음경/일반","price":822000,"ediCode":"HE1310001","date":"2025-09-03","unit":"-","category":"-"},{"hospName":"목동병원","itemName":"초음파검사료(기본초음파)/단순초음파/Ⅱ","price":160000,"ediCode":"EB4020000","date":"2025-09-03","unit":"-","category":"-"},{"hospName":"목동병원","itemName":"초음파검사료(기본초음파)/단순초음파/Ⅱ","price":211000,"ediCode":"EB4020000","date":"2025-09-03","unit":"-","category":"-"},{"hospName":"목동병원","itemName":"처치 및 수술료(기타)/경두개자기자극술","price":71100,"ediCode":"QZ9620000","date":"2025-09-03","unit":"-","category":"-"},{"hospName":"목동병원","itemName":"초음파 검사료(유도 초음파)/유도초음파/Ⅱ","price":242000,"ediCode":"EB5620000","date":"2025-09-03","unit":"-","category":"-"},{"hospName":"목동병원","itemName":"기능 검사료(신경계 기능검사)/정량적감각기능검사/온도역치","price":49200,"ediCode":"FY8820000","date":"2025-09-03","unit":"-","category":"-"},{"hospName":"목동병원","itemName":"기능 검사료(외피, 근골 기능 검사)/동적 족저압측정","price":54700,"ediCode":"EZ7770000","date":"2025-09-03","unit":"-","category":"-"},{"hospName":"목동병원","itemName":"기능 검사료(평형 및 청각 기능검사)/회전검사","price":76500,"ediCode":"FZ7320000","date":"2025-09-03","unit":"-","category":"-"},{"hospName":"목동병원","itemName":"초음파 검사료(유도 초음파)/수술 중 초음파","price":168000,"ediCode":"EZ9850000","date":"2025-09-03","unit":"-","category":"-"},{"hospName":"목동병원","itemName":"자기공명영상진단료(MRI-특수검사)/Dynamic [기본검사 포함]","price":709400,"ediCode":"HF1050000","date":"2025-09-03","unit":"-","category":"-"},{"hospName":"목동병원","itemName":"기능 검사료(순환기 기능 검사)/정맥역류검사","price":156100,"ediCode":"EZ8670000","date":"2025-09-03","unit":"-","category":"-"},{"hospName":"목동병원","itemName":"자기공명영상진단료(MRI-특수검사)/영화 [기본검사 및 3차원자기공명영상 포함]","price":650000,"ediCode":"HF1040000","date":"2025-09-03","unit":"-","category":"-"},{"hospName":"목동병원","itemName":"기능 검사료(순환기 기능 검사)/동맥경화도검사(맥파전달속도측정)","price":49200,"ediCode":"EZ8680000","date":"2025-09-03","unit":"-","category":"-"},{"hospName":"목동병원","itemName":"초음파 검사료(유도 초음파)/유도초음파/Ⅱ","price":327000,"ediCode":"EB5620000","date":"2025-09-03","unit":"-","category":"-"},{"hospName":"목동병원","itemName":"처치 및 수술료(기타)/경두개자기자극술","price":125700,"ediCode":"QZ9620000","date":"2025-09-03","unit":"-","category":"-"},{"hospName":"목동병원","itemName":"치료재료/척추경막외 유착방지제/수술엔(SUSUL N)","price":290000,"ediCode":"BF0100SX","date":"2025-09-03","unit":"-","category":"-"},{"hospName":"목동병원","itemName":"기능 검사료(평형 및 청각 기능검사)/회전검사","price":87400,"ediCode":"FZ7320000","date":"2025-09-03","unit":"-","category":"-"},{"hospName":"목동병원","itemName":"초음파검사료(진단초음파)/혈관-사지혈관 도플러 초음파/동정맥루의 혈류 및 협착 측정 시","price":328000,"ediCode":"EB4860000","date":"2025-09-03","unit":"-","category":"-"},{"hospName":"목동병원","itemName":"치과 처치· 수술료/광중합형 복합레진 충전/우식-1면","price":130000,"ediCode":"U02390000","date":"2025-09-03","unit":"-","category":"-"},{"hospName":"목동병원","itemName":"제증명수수료/확인서/입퇴원","price":3000,"ediCode":"PDZ090002","date":"2025-09-03","unit":"-","category":"-"},{"hospName":"목동병원","itemName":"검체검사료/비침습적 산전검사(NIPT)","price":346500,"ediCode":"3Z2600001","date":"2025-09-03","unit":"-","category":"-"},{"hospName":"목동병원","itemName":"치료재료/재조합골형성단백질(RHBMP-2) 함유 골이식재/INFUSE RHBMP-2 BONE GRAFT","price":3960000,"ediCode":"BC0301AW","date":"2025-10-27","unit":"-","category":"-"},{"hospName":"목동병원","itemName":"초음파 검사료(유도 초음파)/유도초음파/Ⅰ","price":101000,"ediCode":"EB5610000","date":"2025-09-03","unit":"-","category":"-"},{"hospName":"목동병원","itemName":"초음파검사료(진단초음파)/복부-남성생식기 초음파/전립선·정낭","price":183000,"ediCode":"EB4510001","date":"2025-09-03","unit":"-","category":"-"},{"hospName":"목동병원","itemName":"초음파검사료(기본초음파)/단순초음파/Ⅰ","price":54000,"ediCode":"EB4010000","date":"2025-09-03","unit":"-","category":"-"},{"hospName":"목동병원","itemName":"검체검사료/호산구양이온단백농도측정검사","price":56300,"ediCode":"CZ1140000","date":"2025-09-03","unit":"-","category":"-"},{"hospName":"목동병원","itemName":"자기공명영상진단료(MRI-기본검사)/근골격계-관절외 하지/조영제 주입 전·후 촬영 판독","price":819000,"ediCode":"HE2230000","date":"2025-09-03","unit":"-","category":"-"},{"hospName":"목동병원","itemName":"제증명수수료/진료기록영상/DVD","price":20000,"ediCode":"PDZ110005","date":"2025-09-03","unit":"-","category":"-"},{"hospName":"목동병원","itemName":"자기공명영상진단료(MRI-기본검사)/근골격계-수관절/조영제 주입 전·후 촬영 판독","price":819000,"ediCode":"HE2170000","date":"2025-09-03","unit":"-","category":"-"},{"hospName":"목동병원","itemName":"초음파검사료(진단초음파)/근골격, 연부-관절 초음파/손가락","price":105000,"ediCode":"EB4610000","date":"2025-09-03","unit":"-","category":"-"},{"hospName":"목동병원","itemName":"자기공명영상진단료(MRI-기본검사)/근골격계-고관절/일반","price":786000,"ediCode":"HE1180000","date":"2025-09-03","unit":"-","category":"-"},{"hospName":"목동병원","itemName":"초음파검사료(진단초음파)/복부-여성생식기 초음파/일반","price":211000,"ediCode":"EB4550001","date":"2025-09-03","unit":"-","category":"-"},{"hospName":"목동병원","itemName":"기능 검사료(평형 및 청각 기능검사)/회전검사","price":23000,"ediCode":"FZ7320000","date":"2025-09-03","unit":"-","category":"-"},{"hospName":"목동병원","itemName":"자기공명영상진단료(MRI-기본검사)/복부-담췌관/일반","price":491000,"ediCode":"HE1330001","date":"2025-09-03","unit":"-","category":"-"},{"hospName":"목동병원","itemName":"기능 검사료(알레르기 검사)/경구 음식물유발시험과 경구 약물유발시험검사","price":279700,"ediCode":"EZ8480000","date":"2025-09-03","unit":"-","category":"-"},{"hospName":"목동병원","itemName":"초음파검사료(진단초음파)/심장-경흉부 심초음파/전문","price":329000,"ediCode":"EB4330000","date":"2025-09-03","unit":"-","category":"-"},{"hospName":"목동병원","itemName":"초음파 검사료(유도 초음파)/수술 중 초음파","price":384000,"ediCode":"EZ9850000","date":"2025-09-03","unit":"-","category":"-"},{"hospName":"목동병원","itemName":"치과의 보철료/크라운/올세라믹","price":463000,"ediCode":"UW609F340","date":"2025-09-03","unit":"-","category":"-"},{"hospName":"목동병원","itemName":"치료재료/척추경막외 유착방지제/하이배리(HIBARRY)","price":478500,"ediCode":"BF0101VT","date":"2025-10-27","unit":"-","category":"-"},{"hospName":"목동병원","itemName":"치과 처치· 수술료/광중합형 복합레진 충전/우식-3면 이상","price":264300,"ediCode":"U02410000","date":"2025-09-03","unit":"-","category":"-"},{"hospName":"목동병원","itemName":"치료재료/조절성 인공수정체/ACRYSOF IQ PANOPTIX TORIC PRESBYOPIA CORRECTING IOLS","price":2520000,"ediCode":"BI0200EB","date":"2025-09-03","unit":"-","category":"-"},{"hospName":"목동병원","itemName":"기능 검사료(신경계 기능검사)/덴버발달검사","price":1600,"ediCode":"FZ6940000","date":"2025-09-03","unit":"-","category":"-"},{"hospName":"목동병원","itemName":"처치 및 수술료(기타)/로봇 보조 수술 [시술시 소요재료 포함]-다빈치 기기/갑상선악성종양근치수술(갑상선암)","price":5000000,"ediCode":"QZ9610002","date":"2025-09-03","unit":"-","category":"-"},{"hospName":"목동병원","itemName":"이학요법료/도수치료","price":120000,"ediCode":"MX1220000","date":"2025-09-03","unit":"-","category":"-"},{"hospName":"목동병원","itemName":"초음파 검사료(유도 초음파)/유도초음파/Ⅱ","price":282000,"ediCode":"EB5620000","date":"2025-09-03","unit":"-","category":"-"},{"hospName":"목동병원","itemName":"자기공명영상진단료(MRI-특수검사)/분광영상","price":403000,"ediCode":"HF1030000","date":"2025-09-03","unit":"-","category":"-"},{"hospName":"목동병원","itemName":"초음파 검사료(유도 초음파)/수술 중 초음파","price":84000,"ediCode":"EZ9850000","date":"2025-09-03","unit":"-","category":"-"},{"hospName":"목동병원","itemName":"예방접종료/Tdap(파상풍, 디프테리아, 백일해)/부스트릭스프리필드시린지","price":42000,"ediCode":"3Z5201601","date":"2025-09-03","unit":"-","category":"-"},{"hospName":"목동병원","itemName":"기능 검사료(신경계 기능검사)/언어전반진단검사","price":19700,"ediCode":"FZ6890000","date":"2025-09-03","unit":"-","category":"-"},{"hospName":"목동병원","itemName":"이학요법료/이명재훈련치료","price":100000,"ediCode":"MZ0040000","date":"2025-09-03","unit":"-","category":"-"},{"hospName":"목동병원","itemName":"처치 및 수술료(기타)/로봇 보조 수술 [시술시 소요재료 포함]-다빈치 기기/갑상선악성종양근치수술(갑상선암)","price":8000000,"ediCode":"QZ9610002","date":"2025-09-03","unit":"-","category":"-"},{"hospName":"목동병원","itemName":"기능 검사료(신경계 기능검사)/언어전반진단검사","price":191400,"ediCode":"FZ6890000","date":"2025-09-03","unit":"-","category":"-"},{"hospName":"목동병원","itemName":"치과 처치· 수술료/광중합형 복합레진 충전/우식-2면","price":139000,"ediCode":"U02400000","date":"2025-09-03","unit":"-","category":"-"},{"hospName":"목동병원","itemName":"초음파 검사료(유도 초음파)/유도초음파/Ⅳ","price":263000,"ediCode":"EB5640000","date":"2025-09-03","unit":"-","category":"-"},{"hospName":"목동병원","itemName":"제증명수수료/후유장애진단서","price":100000,"ediCode":"PDZ070003","date":"2025-09-03","unit":"-","category":"-"},{"hospName":"목동병원","itemName":"이학요법료/언어치료","price":71100,"ediCode":"MZ0060000","date":"2025-09-03","unit":"-","category":"-"},{"hospName":"목동병원","itemName":"초음파 검사료(유도 초음파)/유도초음파/Ⅰ","price":101000,"ediCode":"EB5610000","date":"2025-09-03","unit":"-","category":"-"},{"hospName":"목동병원","itemName":"초음파검사료(진단초음파)/혈관-사지혈관 도플러 초음파/상지-정맥","price":147000,"ediCode":"EB4850000","date":"2025-09-03","unit":"-","category":"-"},{"hospName":"목동병원","itemName":"기능 검사료(평형 및 청각 기능검사)/비디오전기안진검사","price":39400,"ediCode":"FZ7330000","date":"2025-09-03","unit":"-","category":"-"},{"hospName":"목동병원","itemName":"제증명수수료/장애 정도 심사용 진단서/신체적장애","price":15000,"ediCode":"PDZ070001","date":"2025-09-03","unit":"-","category":"-"},{"hospName":"목동병원","itemName":"치료재료/혈관내영상카테타/OPTICROSS HD CORONARY IMAGING CATHETER","price":1809600,"ediCode":"BJ4505BM","date":"2025-09-03","unit":"-","category":"-"},{"hospName":"목동병원","itemName":"초음파검사료(기본초음파)/단순초음파/Ⅱ","price":200000,"ediCode":"EB4020000","date":"2025-09-03","unit":"-","category":"-"},{"hospName":"목동병원","itemName":"초음파검사료(진단초음파)/혈관-사지혈관 도플러 초음파/상지-동맥","price":229000,"ediCode":"EB4840000","date":"2025-09-03","unit":"-","category":"-"},{"hospName":"목동병원","itemName":"기능 검사료(외피, 근골 기능 검사)/동적 족저압측정","price":82000,"ediCode":"EZ7770000","date":"2025-09-03","unit":"-","category":"-"},{"hospName":"목동병원","itemName":"치료재료/조절성 인공수정체/TECNIS SYNERGY OPTIBLUE IOL, TECNIS SYNERGY OPTIBLUE IOL WITH TECNIS SIMPLICITY DELIVERY SYSTEM","price":2574000,"ediCode":"BI0208LN","date":"2025-09-03","unit":"-","category":"-"},{"hospName":"목동병원","itemName":"초음파검사료(진단초음파)/복부-남성생식기 초음파/음경","price":206000,"ediCode":"EB4530001","date":"2025-09-03","unit":"-","category":"-"},{"hospName":"목동병원","itemName":"자기공명영상진단료(MRI-기본검사)/혈관-뇌혈관/일반","price":725000,"ediCode":"HE1350001","date":"2025-09-03","unit":"-","category":"-"},{"hospName":"목동병원","itemName":"초음파 검사료(유도 초음파)/유도초음파/Ⅰ","price":61000,"ediCode":"EB5610000","date":"2025-09-03","unit":"-","category":"-"},{"hospName":"목동병원","itemName":"초음파검사료(진단초음파)/진단초음파/흉부-유방·액와부 초음파 /자동유방초음파","price":208000,"ediCode":"EB4240000","date":"2025-09-03","unit":"-","category":"-"},{"hospName":"목동병원","itemName":"기능 검사료(외피, 근골 기능 검사)/동적 족저압측정","price":50000,"ediCode":"EZ7770000","date":"2025-09-03","unit":"-","category":"-"},{"hospName":"목동병원","itemName":"기능 검사료(외피, 근골 기능 검사)/관절계를 이용한 무릎관절인대검사","price":241400,"ediCode":"EZ7750000","date":"2025-09-03","unit":"-","category":"-"},{"hospName":"목동병원","itemName":"예방접종료/A형간염/박타프리필드시린지 0.5ml","price":35000,"ediCode":"3Z5202007","date":"2025-09-03","unit":"-","category":"-"},{"hospName":"목동병원","itemName":"자기공명영상진단료(MRI-기본검사)/두경부-측두하악관절/일반","price":786000,"ediCode":"HE1070001","date":"2025-09-03","unit":"-","category":"-"},{"hospName":"목동병원","itemName":"초음파 검사료(유도 초음파)/수술 중 초음파","price":456000,"ediCode":"EZ9850000","date":"2025-09-03","unit":"-","category":"-"},{"hospName":"목동병원","itemName":"예방접종료/일본뇌염/보령세포배양일본뇌염백신주 0.4mL","price":31000,"ediCode":"3Z5201203","date":"2025-09-03","unit":"-","category":"-"},{"hospName":"목동병원","itemName":"예방접종료/대상포진/조스타박스주","price":180000,"ediCode":"3Z5200302","date":"2025-09-03","unit":"-","category":"-"},{"hospName":"목동병원","itemName":"기능 검사료(신경계 기능검사)/발음 및 발성검사","price":29000,"ediCode":"FZ6880000","date":"2025-09-03","unit":"-","category":"-"},{"hospName":"목동병원","itemName":"기능 검사료(시기능검사)/간섭에 의한 눈물 지질층 두께 측정","price":50000,"ediCode":"EZ7990000","date":"2025-09-03","unit":"-","category":"-"},{"hospName":"목동병원","itemName":"초음파검사료(진단초음파)/복부-복부 초음파/간·담낭·담도·비장·췌장-정밀","price":256000,"ediCode":"EB4420000","date":"2025-09-03","unit":"-","category":"-"},{"hospName":"목동병원","itemName":"초음파검사료(진단초음파)/근골격, 연부-관절 초음파/견관절","price":105000,"ediCode":"EB4660000","date":"2025-09-03","unit":"-","category":"-"},{"hospName":"목동병원","itemName":"기능 검사료(신경계 기능검사)/초음파를 활용한 뇌혈류 기능검사","price":146000,"ediCode":"FZ7140000","date":"2025-09-03","unit":"-","category":"-"},{"hospName":"목동병원","itemName":"치료재료/조절성 인공수정체/TECNIS SYNERGY TORIC II OPTIBLUE IOL, TECNIS SYNERGY TORIC II OPTIBLUE IOL WITH TECNIS SIMPLICITY DELIVERY SYSTEM","price":2508000,"ediCode":"BI0209LN","date":"2025-09-03","unit":"-","category":"-"},{"hospName":"목동병원","itemName":"이학요법료/비침습적 무통증 신호요법","price":61000,"ediCode":"MZ0120000","date":"2025-09-03","unit":"-","category":"-"},{"hospName":"목동병원","itemName":"초음파 검사료(유도 초음파)/유도초음파/Ⅱ","price":369000,"ediCode":"EB5620000","date":"2025-09-03","unit":"-","category":"-"},{"hospName":"목동병원","itemName":"치과 처치· 수술료/광중합형 복합레진 충전/우식-1면","price":228600,"ediCode":"U02390000","date":"2025-09-03","unit":"-","category":"-"},{"hospName":"목동병원","itemName":"초음파검사료(진단초음파)/혈관-사지혈관 도플러 초음파/상지-동맥","price":164000,"ediCode":"EB4840000","date":"2025-09-03","unit":"-","category":"-"},{"hospName":"목동병원","itemName":"치료재료/조절성 인공수정체/테크니스 퓨어SEE","price":2093000,"ediCode":"BI0212LN","date":"2025-09-03","unit":"-","category":"-"},{"hospName":"목동병원","itemName":"치료재료/관상동맥내 광학파 단층촬영용/DRAGONFLY CATHETER","price":2055300,"ediCode":"BJ4513LR","date":"2025-09-03","unit":"-","category":"-"},{"hospName":"목동병원","itemName":"치과 처치· 수술료/광중합형 복합레진 충전/우식-3면 이상","price":198000,"ediCode":"U02410000","date":"2025-09-03","unit":"-","category":"-"},{"hospName":"목동병원","itemName":"이학요법료/언어치료","price":18700,"ediCode":"MZ0060000","date":"2025-09-03","unit":"-","category":"-"},{"hospName":"목동병원","itemName":"기능 검사료(외피, 근골 기능 검사)/동적 족저압측정","price":38300,"ediCode":"EZ7770000","date":"2025-09-03","unit":"-","category":"-"},{"hospName":"목동병원","itemName":"치료재료/고주파 정맥내막폐쇄요법용/VNUS CLOSURE FAST","price":1232000,"ediCode":"BJ4301DU","date":"2025-09-03","unit":"-","category":"-"},{"hospName":"목동병원","itemName":"자기공명영상진단료(MRI-특수검사)/분광영상","price":403000,"ediCode":"HF1030000","date":"2025-09-03","unit":"-","category":"-"},{"hospName":"목동병원","itemName":"초음파 검사료(특수 초음파)/내시경초음파","price":415000,"ediCode":"EZ9920000","date":"2025-09-03","unit":"-","category":"-"},{"hospName":"목동병원","itemName":"예방접종료/사람유두종바이러스 감염증(HPV 백신)/서바릭스프리필드시린지","price":130000,"ediCode":"3Z5201001","date":"2025-09-03","unit":"-","category":"-"},{"hospName":"목동병원","itemName":"치료재료/재조합골형성단백질(RHBMP-2) 함유 골이식재/코웰BMP","price":809200,"ediCode":"BC0301YJ","date":"2025-10-27","unit":"-","category":"-"},{"hospName":"목동병원","itemName":"기능 검사료(호흡기 기능검사)/후각기능(인지 및 역치)검사","price":83000,"ediCode":"FZ6710000","date":"2025-09-03","unit":"-","category":"-"},{"hospName":"목동병원","itemName":"기능 검사료(신경계 기능검사)/초음파를 활용한 뇌혈류 기능검사","price":83000,"ediCode":"FZ7140000","date":"2025-09-03","unit":"-","category":"-"},{"hospName":"목동병원","itemName":"자기공명영상진단료(MRI-기본검사)/흉부-유방/일반","price":822000,"ediCode":"HE1260001","date":"2025-09-03","unit":"-","category":"-"},{"hospName":"목동병원","itemName":"치료재료/갑상선 양성결절의 고주파 열치료용/WELL-POINT RF ELECTRODE","price":991200,"ediCode":"BJ4701GX","date":"2025-09-03","unit":"-","category":"-"},{"hospName":"목동병원","itemName":"초음파 검사료(특수 초음파)/기관지내시경초음파 [가이드시스를 이용한 경우 포함]/기관지내시경초음파","price":491000,"ediCode":"EZ9910001","date":"2025-09-03","unit":"-","category":"-"},{"hospName":"목동병원","itemName":"초음파 검사료(유도 초음파)/유도초음파/Ⅱ","price":315000,"ediCode":"EB5620000","date":"2025-09-03","unit":"-","category":"-"},{"hospName":"목동병원","itemName":"치과 처치· 수술료/광중합형 복합레진 충전/우식-3면 이상","price":176000,"ediCode":"U02410000","date":"2025-09-03","unit":"-","category":"-"},{"hospName":"목동병원","itemName":"처치 및 수술료(근골)/추간판내 고주파 열치료술","price":700000,"ediCode":"SZ0830000","date":"2025-09-03","unit":"-","category":"-"},{"hospName":"목동병원","itemName":"자기공명영상진단료(MRI-기본검사)/복부-전립선/일반","price":786000,"ediCode":"HE1340001","date":"2025-09-03","unit":"-","category":"-"},{"hospName":"목동병원","itemName":"기능 검사료(호흡기 기능검사)/후각기능(인지 및 역치)검사","price":50000,"ediCode":"FZ6710000","date":"2025-09-03","unit":"-","category":"-"},{"hospName":"목동병원","itemName":"치료재료/동종진피(IMPLANT용-유방재건술용 제외)/WITHDERM","price":1232000,"ediCode":"BTS01225","date":"2025-10-27","unit":"-","category":"-"},{"hospName":"목동병원","itemName":"기능 검사료(평형 및 청각 기능검사)/회전검사","price":209900,"ediCode":"FZ7320000","date":"2025-09-03","unit":"-","category":"-"},{"hospName":"목동병원","itemName":"치과 처치· 수술료/인레이(Inlay) 및 온레이(Onlay) 간접충전(금 등을 사용한 충전치료)-인레이/레진","price":242000,"ediCode":"UZ0040012","date":"2025-09-03","unit":"-","category":"-"},{"hospName":"목동병원","itemName":"초음파검사료(기본초음파)/단순초음파/Ⅱ","price":107000,"ediCode":"EB4020000","date":"2025-09-03","unit":"-","category":"-"},{"hospName":"목동병원","itemName":"자기공명영상진단료(MRI-기본검사)/근골격계-관절외 상지/일반","price":786000,"ediCode":"HE1220000","date":"2025-09-03","unit":"-","category":"-"},{"hospName":"목동병원","itemName":"치료재료/척추경막외 유착방지제/하이배리(HIBARRY)","price":319000,"ediCode":"BF0101VT","date":"2025-09-03","unit":"-","category":"-"},{"hospName":"목동병원","itemName":"처치 및 수술료(근골)/체외충격파치료[근골격계질환]","price":68900,"ediCode":"SZ0840000","date":"2025-09-03","unit":"-","category":"-"},{"hospName":"목동병원","itemName":"기능 검사료(신경계 기능검사)/주의력검사","price":78600,"ediCode":"FZ6900000","date":"2025-09-03","unit":"-","category":"-"},{"hospName":"목동병원","itemName":"초음파검사료(기본초음파)/단순초음파/Ⅱ","price":126000,"ediCode":"EB4020000","date":"2025-09-03","unit":"-","category":"-"},{"hospName":"목동병원","itemName":"예방접종료/장티푸스/지로티프-주","price":32200,"ediCode":"3Z5201401","date":"2025-09-03","unit":"-","category":"-"},{"hospName":"목동병원","itemName":"초음파검사료(기본초음파)/단순초음파/Ⅱ","price":95000,"ediCode":"EB4020000","date":"2025-09-03","unit":"-","category":"-"},{"hospName":"목동병원","itemName":"치료재료/동종진피(IMPLANT용-유방재건술용 제외)/MEGADERM","price":78400,"ediCode":"BTS01019","date":"2025-09-03","unit":"-","category":"-"},{"hospName":"목동병원","itemName":"초음파검사료(진단초음파)/복부-복부 초음파/서혜부","price":197000,"ediCode":"EB4450001","date":"2025-09-03","unit":"-","category":"-"},{"hospName":"목동병원","itemName":"자기공명영상진단료(MRI-특수검사)/기능적 [기본검사 및 3차원자기공명영상 포함]","price":819000,"ediCode":"HF1070000","date":"2025-09-03","unit":"-","category":"-"},{"hospName":"목동병원","itemName":"초음파검사료(진단초음파)/임산부 초음파/제2,3삼분기 -정밀","price":250000,"ediCode":"EB5170000","date":"2025-09-03","unit":"-","category":"-"},{"hospName":"목동병원","itemName":"자기공명영상진단료(MRI-기본검사)/근골격계-슬관절/조영제 주입 전·후 촬영 판독","price":819000,"ediCode":"HE2200000","date":"2025-09-03","unit":"-","category":"-"},{"hospName":"목동병원","itemName":"초음파검사료(기본초음파)/단순초음파/Ⅱ","price":61000,"ediCode":"EB4020000","date":"2025-09-03","unit":"-","category":"-"},{"hospName":"목동병원","itemName":"기능 검사료(신경계 기능검사)/발음 및 발성검사","price":54700,"ediCode":"FZ6880000","date":"2025-09-03","unit":"-","category":"-"},{"hospName":"목동병원","itemName":"초음파 검사료(유도 초음파)/유도초음파/Ⅱ","price":305000,"ediCode":"EB5620000","date":"2025-09-03","unit":"-","category":"-"},{"hospName":"목동병원","itemName":"치료재료/유방 생검용/ENCOR BIOPSY PROBES(PROBE + RINSE/VACUUM TUBINHG ASSEMBLY)","price":565500,"ediCode":"BM0002GU","date":"2025-09-03","unit":"-","category":"-"},{"hospName":"목동병원","itemName":"초음파 검사료(특수 초음파)/기관지내시경초음파 [가이드시스를 이용한 경우 포함]/기관지내시경초음파 [가이드시스를 이용한 경우]","price":759000,"ediCode":"EZ9910002","date":"2025-09-03","unit":"-","category":"-"},{"hospName":"목동병원","itemName":"초음파 검사료(유도 초음파)/유도초음파/Ⅰ","price":101000,"ediCode":"EB5610000","date":"2025-09-03","unit":"-","category":"-"},{"hospName":"목동병원","itemName":"초음파검사료(진단초음파)/근골격, 연부-관절 초음파/고관절","price":84000,"ediCode":"EB4650000","date":"2025-09-03","unit":"-","category":"-"},{"hospName":"목동병원","itemName":"초음파 검사료(유도 초음파)/유도초음파/Ⅱ","price":315000,"ediCode":"EB5620000","date":"2025-09-03","unit":"-","category":"-"},{"hospName":"목동병원","itemName":"초음파검사료(진단초음파)/근골격, 연부-관절 초음파/손가락","price":105000,"ediCode":"EB4610000","date":"2025-09-03","unit":"-","category":"-"},{"hospName":"목동병원","itemName":"초음파 검사료(특수 초음파)/심장-심장내 초음파","price":1106000,"ediCode":"EB6120000","date":"2025-09-03","unit":"-","category":"-"},{"hospName":"목동병원","itemName":"치과 처치· 수술료/광중합형 복합레진 충전/우식-1면","price":104000,"ediCode":"U02390000","date":"2025-09-03","unit":"-","category":"-"},{"hospName":"목동병원","itemName":"이학요법료/도수치료","price":60000,"ediCode":"MX1220000","date":"2025-09-03","unit":"-","category":"-"},{"hospName":"목동병원","itemName":"이학요법료/신장분사치료","price":20800,"ediCode":"MZ0070000","date":"2025-09-03","unit":"-","category":"-"},{"hospName":"목동병원","itemName":"치과의 보철료/크라운/Gold","price":600000,"ediCode":"UW607F320","date":"2025-09-03","unit":"-","category":"-"},{"hospName":"목동병원","itemName":"자기공명영상진단료(MRI-기본검사)/혈관-경부혈관/일반","price":786000,"ediCode":"HE1360001","date":"2025-09-03","unit":"-","category":"-"},{"hospName":"목동병원","itemName":"자기공명영상진단료(MRI-기본검사)/복부-췌장/일반","price":822000,"ediCode":"HE1290001","date":"2025-09-03","unit":"-","category":"-"},{"hospName":"목동병원","itemName":"초음파검사료(기본초음파)/단순초음파/Ⅱ","price":95000,"ediCode":"EB4020000","date":"2025-09-03","unit":"-","category":"-"},{"hospName":"목동병원","itemName":"기능 검사료(호흡기 기능검사)/호기 산화질소 측정","price":56100,"ediCode":"FZ6720000","date":"2025-09-03","unit":"-","category":"-"},{"hospName":"목동병원","itemName":"치료재료/척추경막외 유착방지제/큐블럭(QBLOCK)","price":594500,"ediCode":"BF0101WC","date":"2025-10-22","unit":"-","category":"-"},{"hospName":"목동병원","itemName":"기능 검사료 (치아검사)/인상채득 및 모형제작 [1악당]","price":27000,"ediCode":"EX9340000","date":"2025-09-03","unit":"-","category":"-"},{"hospName":"목동병원","itemName":"초음파 검사료(유도 초음파)/유도초음파/Ⅰ","price":286000,"ediCode":"EB5610000","date":"2025-09-03","unit":"-","category":"-"},{"hospName":"목동병원","itemName":"초음파 검사료(유도 초음파)/진공보조 유방 생검시 유도 초음파","price":1748000,"ediCode":"EZ9870000","date":"2025-09-03","unit":"-","category":"-"},{"hospName":"목동병원","itemName":"초음파검사료(진단초음파)/근골격, 연부-관절 초음파/손목관절","price":84000,"ediCode":"EB4670000","date":"2025-09-03","unit":"-","category":"-"},{"hospName":"목동병원","itemName":"치과의 보철료/크라운/Gold","price":500000,"ediCode":"UW607F320","date":"2025-09-03","unit":"-","category":"-"},{"hospName":"목동병원","itemName":"초음파 검사료(유도 초음파)/수술 중 초음파","price":775000,"ediCode":"EZ9850000","date":"2025-09-03","unit":"-","category":"-"},{"hospName":"목동병원","itemName":"자기공명영상진단료(MRI-기본검사)/흉부-흉부/일반","price":786000,"ediCode":"HE1250001","date":"2025-09-03","unit":"-","category":"-"},{"hospName":"목동병원","itemName":"초음파검사료(진단초음파)/근골격, 연부-관절 초음파/손목관절","price":84000,"ediCode":"EB4670000","date":"2025-09-03","unit":"-","category":"-"},{"hospName":"목동병원","itemName":"내시경, 천자 및 생검료 /진정내시경환자관리료 /Ⅱ","price":139000,"ediCode":"EA0020000","date":"2025-09-03","unit":"-","category":"-"},{"hospName":"목동병원","itemName":"처치 및 수술료(근골)/체외충격파치료[근골격계질환]","price":172600,"ediCode":"SZ0840000","date":"2025-09-03","unit":"-","category":"-"},{"hospName":"목동병원","itemName":"초음파 검사료(유도 초음파)/유도초음파/Ⅰ","price":107000,"ediCode":"EB5610000","date":"2025-09-03","unit":"-","category":"-"},{"hospName":"목동병원","itemName":"초음파검사료(진단초음파)/혈관-사지혈관 도플러 초음파/하지-동맥","price":216000,"ediCode":"EB4870000","date":"2025-09-03","unit":"-","category":"-"},{"hospName":"목동병원","itemName":"초음파검사료(진단초음파)/혈관-대동맥 도플러 초음파","price":166000,"ediCode":"EB4900000","date":"2025-09-03","unit":"-","category":"-"},{"hospName":"목동병원","itemName":"초음파 검사료(유도 초음파)/유도초음파/Ⅰ","price":107000,"ediCode":"EB5610000","date":"2025-09-03","unit":"-","category":"-"},{"hospName":"목동병원","itemName":"초음파검사료(진단초음파)/혈관-뇌혈류 초음파","price":153000,"ediCode":"EB4810000","date":"2025-09-03","unit":"-","category":"-"},{"hospName":"목동병원","itemName":"기능 검사료(외피, 근골 기능 검사)/체온열검사/전신","price":204000,"ediCode":"EZ7760001","date":"2025-10-22","unit":"-","category":"-"},{"hospName":"목동병원","itemName":"치료재료/조절성 인공수정체/테크니스 퓨어SEE 토릭","price":1987700,"ediCode":"BI0213LN","date":"2025-09-03","unit":"-","category":"-"},{"hospName":"목동병원","itemName":"기능 검사료(신경계 기능검사)/섭식장애평가","price":13200,"ediCode":"FZ6850000","date":"2025-09-03","unit":"-","category":"-"},{"hospName":"목동병원","itemName":"기능 검사료(신경계 기능검사)/정량적감각기능검사/전류인지역치","price":47000,"ediCode":"FY8830000","date":"2025-09-03","unit":"-","category":"-"},{"hospName":"목동병원","itemName":"제증명수수료/장애 정도 심사용 진단서/정신적장애","price":40000,"ediCode":"PDZ070002","date":"2025-09-03","unit":"-","category":"-"},{"hospName":"목동병원","itemName":"기능 검사료(신경계 기능검사)/정량적감각기능검사/진동역치","price":51000,"ediCode":"FY8810000","date":"2025-09-03","unit":"-","category":"-"},{"hospName":"목동병원","itemName":"처치 및 수술료(코)/비밸브재건술","price":1020000,"ediCode":"OZ1110000","date":"2025-09-03","unit":"-","category":"-"},{"hospName":"목동병원","itemName":"초음파 검사료(유도 초음파)/수술 중 초음파","price":53000,"ediCode":"EZ9850000","date":"2025-09-03","unit":"-","category":"-"},{"hospName":"목동병원","itemName":"초음파 검사료(유도 초음파)/유도초음파/Ⅰ","price":54000,"ediCode":"EB5610000","date":"2025-09-03","unit":"-","category":"-"},{"hospName":"목동병원","itemName":"교육상담료/당뇨병교육","price":21800,"ediCode":"AZ0010000","date":"2025-09-03","unit":"-","category":"-"},{"hospName":"목동병원","itemName":"초음파검사료(진단초음파)/근골격, 연부-관절 초음파/발목관절","price":105000,"ediCode":"EB4680000","date":"2025-09-03","unit":"-","category":"-"},{"hospName":"목동병원","itemName":"기능 검사료(순환기 기능 검사)/동맥경화도검사(맥파전달속도측정)","price":104900,"ediCode":"EZ8680000","date":"2025-09-03","unit":"-","category":"-"},{"hospName":"목동병원","itemName":"기능 검사료(순환기 기능 검사)/동맥경화도검사(맥파전달속도측정)","price":72800,"ediCode":"EZ8680000","date":"2025-09-03","unit":"-","category":"-"},{"hospName":"목동병원","itemName":"처치 및 수술료(근골)/체외충격파치료[근골격계질환]","price":68600,"ediCode":"SZ0840000","date":"2025-09-03","unit":"-","category":"-"},{"hospName":"목동병원","itemName":"제증명수수료/국민연금 장애 심사용 진단서","price":15000,"ediCode":"PDZ100000","date":"2025-09-03","unit":"-","category":"-"},{"hospName":"목동병원","itemName":"예방접종료/폐렴구균/프리베나13주","price":130000,"ediCode":"3Z5201701","date":"2025-09-03","unit":"-","category":"-"},{"hospName":"목동병원","itemName":"치료재료/척추경막외 유착방지제/수술엔(SUSUL N)","price":366000,"ediCode":"BF0100SX","date":"2025-09-03","unit":"-","category":"-"},{"hospName":"목동병원","itemName":"기능 검사료(신경계 기능검사)/언어전반진단검사","price":30000,"ediCode":"FZ6890000","date":"2025-09-03","unit":"-","category":"-"},{"hospName":"목동병원","itemName":"치료재료/척추경막외 유착방지제/GUARDIX-SP PLUS(가딕스-SP PLUS),BARRIX(배릭스)","price":609000,"ediCode":"BM2103JO","date":"2025-09-03","unit":"-","category":"-"},{"hospName":"목동병원","itemName":"처치 및 수술료(기타)/로봇 보조 수술 [시술시 소요재료 포함]-다빈치 기기/갑상선악성종양근치수술(갑상선암)","price":15000000,"ediCode":"QZ9610002","date":"2025-09-03","unit":"-","category":"-"},{"hospName":"목동병원","itemName":"치료재료/척추경막외 유착방지제/AMMI GUARD,GUARDIANWRAP,MEGABARRY, MCSHIELD (맥쉴드)","price":507500,"ediCode":"BF0101BA","date":"2025-09-03","unit":"-","category":"-"},{"hospName":"목동병원","itemName":"이학요법료/비침습적 무통증 신호요법","price":82000,"ediCode":"MZ0120000","date":"2025-09-03","unit":"-","category":"-"},{"hospName":"목동병원","itemName":"치료재료/조절성 인공수정체/TECNIS SYMFONY TORIC EXTENDED RANGE OF VISION IOL, TECNIS SYMFONY PLUS TORIC EXTENDED RANGE OF VISION IOL","price":3120000,"ediCode":"BI0206LN","date":"2025-09-03","unit":"-","category":"-"},{"hospName":"목동병원","itemName":"기능 검사료(신경계 기능검사)/언어전반진단검사","price":209700,"ediCode":"FZ6890000","date":"2025-09-03","unit":"-","category":"-"},{"hospName":"목동병원","itemName":"기능 검사료(호흡기 기능검사)/후각기능(인지 및 역치)검사","price":46800,"ediCode":"FZ6710000","date":"2025-09-03","unit":"-","category":"-"},{"hospName":"목동병원","itemName":"치과 처치· 수술료/광중합형 복합레진 충전/우식-2면","price":170000,"ediCode":"U02400000","date":"2025-09-03","unit":"-","category":"-"},{"hospName":"목동병원","itemName":"기능 검사료(신경계 기능검사)/교감신경피부반응검사","price":71100,"ediCode":"FZ6810000","date":"2025-09-03","unit":"-","category":"-"},{"hospName":"목동병원","itemName":"치과 처치· 수술료/인레이(Inlay) 및 온레이(Onlay) 간접충전(금 등을 사용한 충전치료)-인레이/금","price":396000,"ediCode":"UZ0040011","date":"2025-09-03","unit":"-","category":"-"},{"hospName":"목동병원","itemName":"초음파 검사료(유도 초음파)/유도초음파/Ⅳ","price":422000,"ediCode":"EB5640000","date":"2025-09-03","unit":"-","category":"-"},{"hospName":"목동병원","itemName":"초음파검사료(진단초음파)/근골격, 연부-관절 초음파/발가락","price":105000,"ediCode":"EB4620000","date":"2025-09-03","unit":"-","category":"-"},{"hospName":"목동병원","itemName":"이학요법료/FIMS(Functional Intramuscular Stimulation)","price":27300,"ediCode":"MZ0010000","date":"2025-09-03","unit":"-","category":"-"},{"hospName":"목동병원","itemName":"초음파 검사료(유도 초음파)/유도초음파/Ⅰ","price":211000,"ediCode":"EB5610000","date":"2025-09-03","unit":"-","category":"-"},{"hospName":"목동병원","itemName":"기능 검사료(신경계 기능검사)/언어전반진단검사","price":104000,"ediCode":"FZ6890000","date":"2025-09-03","unit":"-","category":"-"},{"hospName":"목동병원","itemName":"자기공명영상진단료(MRI-기본검사)/뇌/일반","price":786000,"ediCode":"HE1010001","date":"2025-09-03","unit":"-","category":"-"},{"hospName":"목동병원","itemName":"이학요법료/FIMS(Functional Intramuscular Stimulation)","price":167200,"ediCode":"MZ0010000","date":"2025-09-03","unit":"-","category":"-"},{"hospName":"목동병원","itemName":"이학요법료/도수치료","price":60000,"ediCode":"MX1220000","date":"2025-09-03","unit":"-","category":"-"},{"hospName":"목동병원","itemName":"초음파 검사료(유도 초음파)/수술 중 초음파","price":456000,"ediCode":"EZ9850000","date":"2025-09-03","unit":"-","category":"-"},{"hospName":"목동병원","itemName":"예방접종료/Td(파상풍, 디프테리아)/녹십자티디백신프리필드시린지주","price":33000,"ediCode":"3Z5201502","date":"2025-09-03","unit":"-","category":"-"},{"hospName":"목동병원","itemName":"자기공명영상진단료(MRI-기본검사)/복부-신장 및 부신/일반","price":822000,"ediCode":"HE1300001","date":"2025-09-03","unit":"-","category":"-"},{"hospName":"목동병원","itemName":"기능 검사료(평형 및 청각 기능검사)/비디오전기안진검사","price":25200,"ediCode":"FZ7330000","date":"2025-09-03","unit":"-","category":"-"},{"hospName":"목동병원","itemName":"초음파 검사료(유도 초음파)/유도초음파/Ⅱ","price":327000,"ediCode":"EB5620000","date":"2025-09-03","unit":"-","category":"-"},{"hospName":"목동병원","itemName":"치료재료/동종진피(IMPLANT용-유방재건술용 제외)/SCDERM IMPLANT","price":80000,"ediCode":"BTS01097","date":"2025-10-22","unit":"-","category":"-"},{"hospName":"목동병원","itemName":"초음파 검사료(특수 초음파)/내시경초음파","price":383000,"ediCode":"EZ9920000","date":"2025-09-03","unit":"-","category":"-"},{"hospName":"목동병원","itemName":"이학요법료/증식치료/사지관절부위","price":29600,"ediCode":"MY1420000","date":"2025-09-03","unit":"-","category":"-"},{"hospName":"목동병원","itemName":"기능 검사료(신경계 기능검사)/발음 및 발성검사","price":45900,"ediCode":"FZ6880000","date":"2025-09-03","unit":"-","category":"-"},{"hospName":"목동병원","itemName":"초음파검사료(진단초음파)/근골격, 연부-관절 초음파/발가락","price":105000,"ediCode":"EB4620000","date":"2025-09-03","unit":"-","category":"-"},{"hospName":"목동병원","itemName":"초음파검사료(진단초음파)/근골격, 연부-연부조직 초음파/일반","price":211000,"ediCode":"EB4700000","date":"2025-09-03","unit":"-","category":"-"},{"hospName":"목동병원","itemName":"치료재료/척추경막외 유착방지제/MEDICLORE","price":565500,"ediCode":"BM2101QT","date":"2025-10-22","unit":"-","category":"-"},{"hospName":"목동병원","itemName":"자기공명영상진단료(MRI-기본검사)/척추-전척추/일반","price":926100,"ediCode":"HE1130000","date":"2025-09-03","unit":"-","category":"-"},{"hospName":"목동병원","itemName":"치료재료/시아노아크릴레이트를 이용한 복재정맥 폐색술용/VENASEAL CLOSURE SYSTEM","price":2210000,"ediCode":"BJ4321DU","date":"2025-09-03","unit":"-","category":"-"},{"hospName":"목동병원","itemName":"기능 검사료(신경계 기능검사)/초음파를 활용한 뇌혈류 기능검사","price":83000,"ediCode":"FZ7140000","date":"2025-09-03","unit":"-","category":"-"},{"hospName":"목동병원","itemName":"기능 검사료(신경계 기능검사)/자율신경계이상검사/발살바법","price":32700,"ediCode":"FY8920000","date":"2025-09-03","unit":"-","category":"-"},{"hospName":"목동병원","itemName":"초음파 검사료(특수 초음파)/혈관내초음파","price":180000,"ediCode":"EZ9940000","date":"2025-10-27","unit":"-","category":"-"},{"hospName":"목동병원","itemName":"치과 처치· 수술료/광중합형 복합레진 충전/우식-3면 이상","price":286400,"ediCode":"U02410000","date":"2025-09-03","unit":"-","category":"-"},{"hospName":"목동병원","itemName":"제증명수수료/출생증명서","price":3000,"ediCode":"PDZ060000","date":"2025-09-03","unit":"-","category":"-"},{"hospName":"목동병원","itemName":"기능 검사료(신경계 기능검사)/덴버발달검사","price":16400,"ediCode":"FZ6940000","date":"2025-09-03","unit":"-","category":"-"},{"hospName":"목동병원","itemName":"초음파검사료(기본초음파)/단순초음파/Ⅱ","price":126000,"ediCode":"EB4020000","date":"2025-09-03","unit":"-","category":"-"},{"hospName":"목동병원","itemName":"초음파 검사료(특수 초음파)/혈관내초음파","price":314000,"ediCode":"EZ9940000","date":"2025-10-27","unit":"-","category":"-"},{"hospName":"목동병원","itemName":"초음파검사료(진단초음파)/신경-중추신경계 초음파/척수","price":243000,"ediCode":"EB5020000","date":"2025-09-03","unit":"-","category":"-"},{"hospName":"목동병원","itemName":"초음파 검사료(유도 초음파)/유도초음파/Ⅰ","price":101000,"ediCode":"EB5610000","date":"2025-09-03","unit":"-","category":"-"},{"hospName":"목동병원","itemName":"초음파 검사료(유도 초음파)/유도초음파/Ⅰ","price":295000,"ediCode":"EB5610000","date":"2025-09-03","unit":"-","category":"-"},{"hospName":"목동병원","itemName":"처치 및 수술료(기타)/로봇 보조 수술 [시술시 소요재료 포함]-다빈치 기기/갑상선악성종양근치수술(갑상선암)","price":11000000,"ediCode":"QZ9610002","date":"2025-09-03","unit":"-","category":"-"},{"hospName":"목동병원","itemName":"치료재료/재조합골형성단백질(RHBMP-2) 함유 골이식재/NOVOSIS","price":1404000,"ediCode":"BC0301QT","date":"2025-10-27","unit":"-","category":"-"},{"hospName":"목동병원","itemName":"초음파 검사료(유도 초음파)/유도초음파/Ⅱ","price":242000,"ediCode":"EB5620000","date":"2025-09-03","unit":"-","category":"-"},{"hospName":"목동병원","itemName":"치료재료/재조합골형성단백질(RHBMP-2) 함유 골이식재/NOVOSIS","price":2161600,"ediCode":"BC0301QT","date":"2025-10-27","unit":"-","category":"-"},{"hospName":"목동병원","itemName":"제증명수수료/사산(사태)증명서","price":10000,"ediCode":"PDZ050000","date":"2025-09-03","unit":"-","category":"-"},{"hospName":"목동병원","itemName":"이학요법료/언어치료","price":69900,"ediCode":"MZ0060000","date":"2025-09-03","unit":"-","category":"-"},{"hospName":"목동병원","itemName":"기능 검사료(신경계 기능검사)/언어전반진단검사","price":25200,"ediCode":"FZ6890000","date":"2025-09-03","unit":"-","category":"-"},{"hospName":"목동병원","itemName":"교육상담료/당뇨병교육","price":32700,"ediCode":"AZ0010000","date":"2025-09-03","unit":"-","category":"-"},{"hospName":"목동병원","itemName":"초음파검사료(진단초음파)/근골격, 연부-관절 초음파/고관절","price":105000,"ediCode":"EB4650000","date":"2025-09-03","unit":"-","category":"-"},{"hospName":"목동병원","itemName":"상급병실료/1인실","price":398000,"ediCode":"ABZ010001","date":"2025-09-03","unit":"-","category":"-"},{"hospName":"목동병원","itemName":"자기공명영상진단료(MRI-기본검사)/근골격계-견관절/일반","price":786000,"ediCode":"HE1150000","date":"2025-09-03","unit":"-","category":"-"},{"hospName":"목동병원","itemName":"자기공명영상진단료(MRI-기본검사)/심장/일반","price":822000,"ediCode":"HE1240001","date":"2025-09-03","unit":"-","category":"-"},{"hospName":"목동병원","itemName":"기능 검사료(순환기 기능 검사)/동맥경화도검사(맥파전달속도측정)","price":124800,"ediCode":"EZ8680000","date":"2025-09-03","unit":"-","category":"-"},{"hospName":"목동병원","itemName":"초음파 검사료(유도 초음파)/유도초음파/Ⅱ","price":327000,"ediCode":"EB5620000","date":"2025-09-03","unit":"-","category":"-"},{"hospName":"목동병원","itemName":"병리검사료/양수염색체검사","price":714100,"ediCode":"3Z2610000","date":"2025-09-03","unit":"-","category":"-"},{"hospName":"목동병원","itemName":"치료재료/척추경막외 유착방지제/X-AD","price":377000,"ediCode":"BF0100BK","date":"2025-09-03","unit":"-","category":"-"},{"hospName":"목동병원","itemName":"이학요법료/도수치료","price":60000,"ediCode":"MX1220000","date":"2025-09-03","unit":"-","category":"-"},{"hospName":"목동병원","itemName":"정신요법료/정신분석적 정신치료","price":80000,"ediCode":"NZ0110000","date":"2025-09-03","unit":"-","category":"-"},{"hospName":"목동병원","itemName":"기능 검사료(신경계 기능검사)/언어전반진단검사","price":90700,"ediCode":"FZ6890000","date":"2025-09-03","unit":"-","category":"-"},{"hospName":"목동병원","itemName":"치과의 보철료/크라운/Gold","price":404000,"ediCode":"UW607F320","date":"2025-09-03","unit":"-","category":"-"},{"hospName":"목동병원","itemName":"예방접종료/b형헤모필루스인플루엔자/유히브주","price":26500,"ediCode":"3Z5202201","date":"2025-09-03","unit":"-","category":"-"},{"hospName":"목동병원","itemName":"자기공명영상진단료(MRI-기본검사)/근골격계-수관절/일반","price":786000,"ediCode":"HE1170000","date":"2025-09-03","unit":"-","category":"-"},{"hospName":"목동병원","itemName":"치료재료/척추경막외 유착방지제/PRECOAT","price":348000,"ediCode":"BF0100QF","date":"2025-09-03","unit":"-","category":"-"},{"hospName":"목동병원","itemName":"자기공명영상진단료(MRI-기본검사)/혈관-복부혈관/일반","price":822000,"ediCode":"HE1380001","date":"2025-09-03","unit":"-","category":"-"},{"hospName":"목동병원","itemName":"기능 검사료(평형 및 청각 기능검사)/동적체평형검사","price":43700,"ediCode":"FZ7310000","date":"2025-09-03","unit":"-","category":"-"},{"hospName":"목동병원","itemName":"기능 검사료(신경계 기능검사)/언어전반진단검사","price":63000,"ediCode":"FZ6890000","date":"2025-09-03","unit":"-","category":"-"},{"hospName":"목동병원","itemName":"정신요법료/기타 행동치료/신경발달중재치료","price":80000,"ediCode":"NZ0090000","date":"2025-09-03","unit":"-","category":"-"},{"hospName":"목동병원","itemName":"초음파검사료(진단초음파)/근골격, 연부-관절 초음파/주관절","price":84000,"ediCode":"EB4630000","date":"2025-09-03","unit":"-","category":"-"},{"hospName":"목동병원","itemName":"자기공명영상진단료(MRI-기본검사)/척추-경추/일반","price":786000,"ediCode":"HE1090000","date":"2025-09-03","unit":"-","category":"-"},{"hospName":"목동병원","itemName":"초음파검사료(진단초음파)/횡파 탄성 초음파 영상","price":54000,"ediCode":"EZ9810000","date":"2025-09-03","unit":"-","category":"-"},{"hospName":"목동병원","itemName":"제증명수수료/진료기록사본/1~5매","price":1000,"ediCode":"PDZ110101","date":"2025-09-03","unit":"-","category":"-"},{"hospName":"목동병원","itemName":"초음파검사료(진단초음파)/복부-비뇨기계 초음파/신장·부신·방광","price":266000,"ediCode":"EB4480001","date":"2025-09-03","unit":"-","category":"-"},{"hospName":"목동병원","itemName":"치과의 보철료/크라운/PFG","price":463000,"ediCode":"UW608F320","date":"2025-09-03","unit":"-","category":"-"},{"hospName":"목동병원","itemName":"치과 처치· 수술료/인레이(Inlay) 및 온레이(Onlay) 간접충전(금 등을 사용한 충전치료)-인레이/도재-세라믹","price":297000,"ediCode":"UZ0040013","date":"2025-09-03","unit":"-","category":"-"},{"hospName":"목동병원","itemName":"예방접종료/대상포진/스카이조스터주","price":123200,"ediCode":"3Z5200301","date":"2025-09-03","unit":"-","category":"-"},{"hospName":"목동병원","itemName":"기능 검사료(신경계 기능검사)/다중수면잠복기검사","price":487300,"ediCode":"FZ7020000","date":"2025-09-03","unit":"-","category":"-"},{"hospName":"목동병원","itemName":"주사료/알레르겐 면역요법","price":540000,"ediCode":"KZ0010000","date":"2025-09-03","unit":"-","category":"-"},{"hospName":"목동병원","itemName":"기능 검사료(신경계 기능검사)/정량적감각기능검사/진동역치","price":30600,"ediCode":"FY8810000","date":"2025-09-03","unit":"-","category":"-"},{"hospName":"목동병원","itemName":"초음파 검사료(유도 초음파)/유도초음파/Ⅰ","price":211000,"ediCode":"EB5610000","date":"2025-09-03","unit":"-","category":"-"},{"hospName":"목동병원","itemName":"처치 및 수술료(기타)/로봇 보조 수술 [시술시 소요재료 포함]-다빈치 기기/갑상선악성종양근치수술(갑상선암)","price":6000000,"ediCode":"QZ9610002","date":"2025-09-03","unit":"-","category":"-"},{"hospName":"목동병원","itemName":"처치 및 수술료(신경)/경피적 풍선확장 경막외강 신경성형","price":520000,"ediCode":"SZ6410000","date":"2025-09-03","unit":"-","category":"-"},{"hospName":"목동병원","itemName":"기능 검사료(생식, 임신 및 분만)/자궁경부확대촬영검사","price":48000,"ediCode":"EZ8860000","date":"2025-09-03","unit":"-","category":"-"},{"hospName":"목동병원","itemName":"초음파검사료(진단초음파)/복부-복부 초음파/직장·항문","price":259000,"ediCode":"EB4460001","date":"2025-09-03","unit":"-","category":"-"},{"hospName":"목동병원","itemName":"초음파검사료(기본초음파)/단순초음파/Ⅱ","price":211000,"ediCode":"EB4020000","date":"2025-09-03","unit":"-","category":"-"},{"hospName":"목동병원","itemName":"초음파 검사료(유도 초음파)/유도초음파/Ⅰ","price":101000,"ediCode":"EB5610000","date":"2025-09-03","unit":"-","category":"-"},{"hospName":"목동병원","itemName":"치료재료/재조합골형성단백질(RHBMP-2) 함유 골이식재/NOVOSIS","price":2210000,"ediCode":"BC0301QT","date":"2025-10-27","unit":"-","category":"-"},{"hospName":"목동병원","itemName":"치료재료/척추경막외 유착방지제/X-AD","price":572800,"ediCode":"BF0100BK","date":"2025-10-22","unit":"-","category":"-"},{"hospName":"목동병원","itemName":"초음파 검사료(특수 초음파)/심장-경식도 심초음파","price":1005000,"ediCode":"EB6110000","date":"2025-09-03","unit":"-","category":"-"},{"hospName":"목동병원","itemName":"기능 검사료(신경계 기능검사)/정량적감각기능검사/전류인지역치(통증역치검사)","price":32700,"ediCode":"FY8840000","date":"2025-09-03","unit":"-","category":"-"},{"hospName":"목동병원","itemName":"초음파 검사료(유도 초음파)/유도초음파/Ⅱ","price":250000,"ediCode":"EB5620000","date":"2025-09-03","unit":"-","category":"-"},{"hospName":"목동병원","itemName":"기능 검사료(신경계 기능검사)/언어전반진단검사","price":119500,"ediCode":"FZ6890000","date":"2025-09-03","unit":"-","category":"-"},{"hospName":"목동병원","itemName":"초음파 검사료(유도 초음파)/유도초음파/Ⅱ","price":171000,"ediCode":"EB5620000","date":"2025-09-03","unit":"-","category":"-"},{"hospName":"목동병원","itemName":"처치 및 수술료(내분비기)/증상이 있는 갑상선양성결절의 고주파열치료술","price":1807000,"ediCode":"PZ6120000","date":"2025-09-03","unit":"-","category":"-"},{"hospName":"목동병원","itemName":"초음파검사료(진단초음파)/근골격, 연부-관절 초음파/손목관절","price":105000,"ediCode":"EB4670000","date":"2025-09-03","unit":"-","category":"-"},{"hospName":"목동병원","itemName":"초음파검사료(진단초음파)/근골격, 연부-관절 초음파/손목관절","price":105000,"ediCode":"EB4670000","date":"2025-09-03","unit":"-","category":"-"},{"hospName":"목동병원","itemName":"치과 처치· 수술료/광중합형 복합레진 충전/우식-3면 이상","price":200000,"ediCode":"U02410000","date":"2025-09-03","unit":"-","category":"-"},{"hospName":"목동병원","itemName":"초음파 검사료(유도 초음파)/유도초음파/Ⅱ","price":250000,"ediCode":"EB5620000","date":"2025-09-03","unit":"-","category":"-"},{"hospName":"목동병원","itemName":"치료재료/척추경막외 유착방지제/MEDICLORE","price":369750,"ediCode":"BM2101QT","date":"2025-09-03","unit":"-","category":"-"},{"hospName":"목동병원","itemName":"제증명수수료/진단서/건강","price":20000,"ediCode":"PDZ010001","date":"2025-09-03","unit":"-","category":"-"},{"hospName":"목동병원","itemName":"기능 검사료(신경계 기능검사)/섭식장애평가","price":16400,"ediCode":"FZ6850000","date":"2025-09-03","unit":"-","category":"-"},{"hospName":"목동병원","itemName":"검체검사료/DHEA(Dehydroepiandrosterone)","price":186600,"ediCode":"CZ1990000","date":"2025-09-03","unit":"-","category":"-"},{"hospName":"목동병원","itemName":"초음파검사료(진단초음파)/근골격, 연부-관절 초음파/견관절","price":105000,"ediCode":"EB4660000","date":"2025-09-03","unit":"-","category":"-"},{"hospName":"목동병원","itemName":"자기공명영상진단료(MRI-특수검사)/확산","price":401300,"ediCode":"HF1010000","date":"2025-09-03","unit":"-","category":"-"},{"hospName":"목동병원","itemName":"초음파검사료(진단초음파)/혈관-두개외 혈관 도플러 초음파/기타동맥","price":275000,"ediCode":"EB4830000","date":"2025-09-03","unit":"-","category":"-"},{"hospName":"목동병원","itemName":"자기공명영상진단료(MRI-기본검사)/근골격계-발목관절/조영제 주입 전·후 촬영 판독","price":819000,"ediCode":"HE2210000","date":"2025-09-03","unit":"-","category":"-"},{"hospName":"목동병원","itemName":"초음파 검사료(유도 초음파)/진공보조 유방 생검시 유도 초음파","price":1094000,"ediCode":"EZ9870000","date":"2025-09-03","unit":"-","category":"-"},{"hospName":"목동병원","itemName":"치과 처치· 수술료/자가치아 이식술","price":385000,"ediCode":"UZ0820000","date":"2025-09-03","unit":"-","category":"-"},{"hospName":"목동병원","itemName":"제증명수수료/진료기록영상/필름","price":5000,"ediCode":"PDZ110003","date":"2025-09-03","unit":"-","category":"-"},{"hospName":"목동병원","itemName":"초음파검사료(진단초음파)/근골격, 연부-연부조직 초음파/일반","price":126000,"ediCode":"EB4700000","date":"2025-09-03","unit":"-","category":"-"},{"hospName":"목동병원","itemName":"초음파검사료(진단초음파)/신경-말초신경 초음파/편측","price":66000,"ediCode":"EB5030000","date":"2025-09-03","unit":"-","category":"-"},{"hospName":"목동병원","itemName":"치과 처치· 수술료/인레이(Inlay) 및 온레이(Onlay) 간접충전(금 등을 사용한 충전치료)-인레이/금","price":208000,"ediCode":"UZ0040011","date":"2025-09-03","unit":"-","category":"-"},{"hospName":"목동병원","itemName":"이학요법료/전산화 인지재활치료[주의·기억]","price":30000,"ediCode":"MZ0090000","date":"2025-09-03","unit":"-","category":"-"},{"hospName":"목동병원","itemName":"기능 검사료(외피, 근골 기능 검사)/체온열검사/부분","price":57900,"ediCode":"EZ7760002","date":"2025-10-22","unit":"-","category":"-"},{"hospName":"목동병원","itemName":"기능 검사료(신경계 기능검사)/미각검사[인지 및 역치검사]","price":18700,"ediCode":"FZ7100000","date":"2025-09-03","unit":"-","category":"-"},{"hospName":"목동병원","itemName":"예방접종료/일본뇌염/보령세포배양일본뇌염백신주 0.7mL","price":36800,"ediCode":"3Z5201204","date":"2025-09-03","unit":"-","category":"-"},{"hospName":"목동병원","itemName":"초음파검사료(진단초음파)/근골격, 연부-관절 초음파/견관절","price":84000,"ediCode":"EB4660000","date":"2025-09-03","unit":"-","category":"-"},{"hospName":"목동병원","itemName":"초음파검사료(진단초음파)/횡파 탄성 초음파 영상","price":54000,"ediCode":"EZ9810000","date":"2025-09-03","unit":"-","category":"-"},{"hospName":"목동병원","itemName":"치과 처치· 수술료/자가치아 이식술","price":771000,"ediCode":"UZ0820000","date":"2025-09-03","unit":"-","category":"-"},{"hospName":"목동병원","itemName":"기능 검사료(외피, 근골 기능 검사)/관절계를 이용한 무릎관절인대검사","price":114800,"ediCode":"EZ7750000","date":"2025-09-03","unit":"-","category":"-"},{"hospName":"목동병원","itemName":"기능 검사료(신경계 기능검사)/수면리듬양상검사","price":28100,"ediCode":"FZ7000000","date":"2025-09-03","unit":"-","category":"-"},{"hospName":"목동병원","itemName":"처치 및 수술료(기타)/경두개자기자극술","price":38300,"ediCode":"QZ9620000","date":"2025-09-03","unit":"-","category":"-"},{"hospName":"목동병원","itemName":"치료재료/재조합골형성단백질(RHBMP-2) 함유 골이식재/NOVOSIS","price":3410000,"ediCode":"BC0301QT","date":"2025-10-27","unit":"-","category":"-"},{"hospName":"목동병원","itemName":"예방접종료/폐렴구균/프로디악스-23프리필드시린지","price":65300,"ediCode":"3Z5201704","date":"2025-09-03","unit":"-","category":"-"},{"hospName":"목동병원","itemName":"이학요법료/FIMS(Functional Intramuscular Stimulation)","price":51400,"ediCode":"MZ0010000","date":"2025-09-03","unit":"-","category":"-"},{"hospName":"목동병원","itemName":"기능 검사료(신경계 기능검사)/덴버발달검사","price":2800,"ediCode":"FZ6940000","date":"2025-09-03","unit":"-","category":"-"},{"hospName":"목동병원","itemName":"치료재료/조절성 인공수정체/TECNIS EYHANCE IOL, TECNIS EYHANCE IOL WITH TECNIS SIMPLICITY DELIVERY SYSTEM","price":638000,"ediCode":"BI0207LN","date":"2025-09-03","unit":"-","category":"-"},{"hospName":"목동병원","itemName":"처치 및 수술료(보조생식술)/해동/기타(배아, 난자, 난소조직, 고환조직)","price":100000,"ediCode":"RZ6430002","date":"2025-10-22","unit":"-","category":"-"},{"hospName":"목동병원","itemName":"초음파검사료(진단초음파)/복부-복부 초음파/소장·대장","price":140000,"ediCode":"EB4440001","date":"2025-09-03","unit":"-","category":"-"},{"hospName":"목동병원","itemName":"초음파검사료(진단초음파)/신경-말초신경 초음파/편측","price":55000,"ediCode":"EB5030000","date":"2025-09-03","unit":"-","category":"-"},{"hospName":"목동병원","itemName":"초음파검사료(진단초음파)/혈관-두개외 혈관 도플러 초음파/경동맥","price":229000,"ediCode":"EB4820000","date":"2025-09-03","unit":"-","category":"-"},{"hospName":"목동병원","itemName":"기능 검사료(신경계 기능검사)/발음 및 발성검사","price":25000,"ediCode":"FZ6880000","date":"2025-09-03","unit":"-","category":"-"},{"hospName":"목동병원","itemName":"초음파검사료(진단초음파)/근골격, 연부-관절 초음파/발목관절","price":84000,"ediCode":"EB4680000","date":"2025-09-03","unit":"-","category":"-"},{"hospName":"목동병원","itemName":"예방접종료/B형간염/유박스비 프리필드주 1.0mL","price":30000,"ediCode":"3Z5202108","date":"2025-09-03","unit":"-","category":"-"},{"hospName":"목동병원","itemName":"초음파검사료(기본초음파)/단순초음파/Ⅰ","price":31000,"ediCode":"EB4010000","date":"2025-09-03","unit":"-","category":"-"},{"hospName":"목동병원","itemName":"처치 및 수술료(기타)/로봇 보조 수술 [시술시 소요재료 포함]-다빈치 기기/갑상선악성종양근치수술(갑상선암)","price":12000000,"ediCode":"QZ9610002","date":"2025-09-03","unit":"-","category":"-"},{"hospName":"목동병원","itemName":"초음파검사료(진단초음파)/심장-부하 심초음파/약물부하","price":1062000,"ediCode":"EB4340000","date":"2025-09-03","unit":"-","category":"-"},{"hospName":"목동병원","itemName":"초음파검사료(진단초음파)/두경부-경부 초음파/갑상선·부갑상선","price":191000,"ediCode":"EB4140000","date":"2025-09-03","unit":"-","category":"-"},{"hospName":"목동병원","itemName":"정신요법료/광치료","price":17400,"ediCode":"NZ0010000","date":"2025-09-03","unit":"-","category":"-"},{"hospName":"목동병원","itemName":"이학요법료/비침습적 무통증 신호요법","price":124800,"ediCode":"MZ0120000","date":"2025-09-03","unit":"-","category":"-"},{"hospName":"목동병원","itemName":"이학요법료/언어치료","price":41800,"ediCode":"MZ0060000","date":"2025-09-03","unit":"-","category":"-"},{"hospName":"목동병원","itemName":"자기공명영상진단료(MRI-기본검사)/근골격계-슬관절/일반","price":786000,"ediCode":"HE1200000","date":"2025-09-03","unit":"-","category":"-"},{"hospName":"목동병원","itemName":"이학요법료/비침습적 무통증 신호요법","price":98800,"ediCode":"MZ0120000","date":"2025-09-03","unit":"-","category":"-"},{"hospName":"목동병원","itemName":"치료재료/척추경막외 유착방지제/MEDICLORE","price":205000,"ediCode":"BM2101QT","date":"2025-09-03","unit":"-","category":"-"},{"hospName":"목동병원","itemName":"초음파검사료(기본초음파)/단순초음파/Ⅰ","price":16000,"ediCode":"EB4010000","date":"2025-09-03","unit":"-","category":"-"},{"hospName":"목동병원","itemName":"초음파 검사료(유도 초음파)/유도초음파/Ⅱ","price":250000,"ediCode":"EB5620000","date":"2025-09-03","unit":"-","category":"-"},{"hospName":"목동병원","itemName":"처치 및 수술료(기타)/로봇 보조 수술 [시술시 소요재료 포함]-다빈치 기기/갑상선악성종양근치수술(갑상선암)","price":13000000,"ediCode":"QZ9610002","date":"2025-09-03","unit":"-","category":"-"},{"hospName":"목동병원","itemName":"초음파 검사료(유도 초음파)/유도초음파/Ⅱ","price":105000,"ediCode":"EB5620000","date":"2025-09-03","unit":"-","category":"-"},{"hospName":"목동병원","itemName":"이학요법료/언어치료","price":65000,"ediCode":"MZ0060000","date":"2025-09-03","unit":"-","category":"-"},{"hospName":"목동병원","itemName":"기능 검사료(신경계 기능검사)/자율신경계이상검사/심박변이도검사","price":30600,"ediCode":"FY8940000","date":"2025-09-03","unit":"-","category":"-"},{"hospName":"목동병원","itemName":"기능 검사료(신경계 기능검사)/정량적감각기능검사/온도역치","price":32700,"ediCode":"FY8820000","date":"2025-09-03","unit":"-","category":"-"},{"hospName":"목동병원","itemName":"제증명수수료/향후진료비추정서/천만원 이상","price":100000,"ediCode":"PDZ140002","date":"2025-09-03","unit":"-","category":"-"},{"hospName":"목동병원","itemName":"이학요법료/전산화 인지재활치료[주의·기억]","price":43700,"ediCode":"MZ0090000","date":"2025-09-03","unit":"-","category":"-"},{"hospName":"목동병원","itemName":"치료재료/재조합골형성단백질(RHBMP-2) 함유 골이식재/코웰BMP","price":287100,"ediCode":"BC0301YJ","date":"2025-10-27","unit":"-","category":"-"},{"hospName":"목동병원","itemName":"초음파 검사료(유도 초음파)/유도초음파/Ⅱ","price":265000,"ediCode":"EB5620000","date":"2025-09-03","unit":"-","category":"-"},{"hospName":"목동병원","itemName":"초음파검사료(진단초음파)/혈관-사지혈관 도플러 초음파/하지-동맥","price":229000,"ediCode":"EB4870000","date":"2025-09-03","unit":"-","category":"-"},{"hospName":"목동병원","itemName":"초음파검사료(진단초음파)/근골격, 연부-관절 초음파/류마티스성 질환에 의한 다발성 관절염","price":84000,"ediCode":"EB4690000","date":"2025-09-03","unit":"-","category":"-"},{"hospName":"목동병원","itemName":"초음파검사료(진단초음파)/두경부-안 초음파/안와","price":172000,"ediCode":"EB4120001","date":"2025-09-03","unit":"-","category":"-"},{"hospName":"목동병원","itemName":"초음파검사료(진단초음파)/신경-중추신경계 초음파/경천문 뇌","price":243000,"ediCode":"EB5010000","date":"2025-09-03","unit":"-","category":"-"},{"hospName":"목동병원","itemName":"예방접종료/수막구균/메낙트라주","price":105000,"ediCode":"3Z5200802","date":"2025-09-03","unit":"-","category":"-"},{"hospName":"목동병원","itemName":"초음파검사료(기본초음파)/단순초음파/Ⅱ","price":86000,"ediCode":"EB4020000","date":"2025-09-03","unit":"-","category":"-"},{"hospName":"목동병원","itemName":"치료재료/재조합골형성단백질(RHBMP-2) 함유 골이식재/NOVOSIS","price":3484800,"ediCode":"BC0301QT","date":"2025-10-27","unit":"-","category":"-"},{"hospName":"목동병원","itemName":"이학요법료/언어치료","price":43700,"ediCode":"MZ0060000","date":"2025-09-03","unit":"-","category":"-"},{"hospName":"목동병원","itemName":"자기공명영상진단료(MRI-기본검사)/두경부-경부/일반","price":819000,"ediCode":"HE1080001","date":"2025-09-03","unit":"-","category":"-"},{"hospName":"목동병원","itemName":"치과 처치· 수술료/광중합형 복합레진 충전/우식-1면","price":77000,"ediCode":"U02390000","date":"2025-09-03","unit":"-","category":"-"},{"hospName":"목동병원","itemName":"초음파검사료(진단초음파)/근골격, 연부-관절 초음파/발가락","price":84000,"ediCode":"EB4620000","date":"2025-09-03","unit":"-","category":"-"},{"hospName":"목동병원","itemName":"예방접종료/수막구균/벡세로프리필드시린지","price":190000,"ediCode":"3Z5200803","date":"2025-09-03","unit":"-","category":"-"},{"hospName":"목동병원","itemName":"예방접종료/수두/스카이바리셀라주","price":33000,"ediCode":"3Z5200702","date":"2025-09-03","unit":"-","category":"-"},{"hospName":"목동병원","itemName":"기능 검사료(신경계 기능검사)/영유아발달검사(한국판덴버발달검사)","price":50000,"ediCode":"FZ6930000","date":"2025-09-03","unit":"-","category":"-"},{"hospName":"목동병원","itemName":"초음파검사료(기본초음파)/단순초음파/Ⅱ","price":50000,"ediCode":"EB4020000","date":"2025-09-03","unit":"-","category":"-"},{"hospName":"목동병원","itemName":"치료재료/척추경막외 유착방지제/INTERBLOCK, GUARDIANWRAP PLUS","price":239300,"ediCode":"BF0100VD","date":"2025-10-27","unit":"-","category":"-"},{"hospName":"목동병원","itemName":"초음파검사료(기본초음파)/단순초음파/Ⅱ","price":72000,"ediCode":"EB4020000","date":"2025-09-03","unit":"-","category":"-"},{"hospName":"목동병원","itemName":"초음파검사료(진단초음파)/혈관-두개외 혈관 도플러 초음파/기타동맥","price":54000,"ediCode":"EB4830000","date":"2025-09-03","unit":"-","category":"-"},{"hospName":"목동병원","itemName":"교육상담료/고혈압교육","price":32700,"ediCode":"AZ0020000","date":"2025-09-03","unit":"-","category":"-"},{"hospName":"목동병원","itemName":"초음파검사료(진단초음파)/근골격, 연부-관절 초음파/슬관절","price":105000,"ediCode":"EB4640000","date":"2025-09-03","unit":"-","category":"-"},{"hospName":"목동병원","itemName":"자기공명영상진단료(MRI-기본검사)/복부-골반/일반","price":786000,"ediCode":"HE1280001","date":"2025-09-03","unit":"-","category":"-"},{"hospName":"목동병원","itemName":"기능 검사료(평형 및 청각 기능검사)/회전검사","price":23000,"ediCode":"FZ7320000","date":"2025-09-03","unit":"-","category":"-"},{"hospName":"목동병원","itemName":"초음파검사료(진단초음파)/복부-비뇨기계 초음파/신장·부신","price":211000,"ediCode":"EB4490001","date":"2025-10-22","unit":"-","category":"-"},{"hospName":"목동병원","itemName":"초음파검사료(진단초음파)/임산부 초음파/제1삼분기 -일반","price":69000,"ediCode":"EB5110000","date":"2025-09-03","unit":"-","category":"-"},{"hospName":"목동병원","itemName":"초음파검사료(진단초음파)/횡파 탄성 초음파 영상","price":74000,"ediCode":"EZ9810000","date":"2025-09-03","unit":"-","category":"-"},{"hospName":"목동병원","itemName":"초음파 검사료(유도 초음파)/유도초음파/Ⅳ","price":775000,"ediCode":"EB5640000","date":"2025-09-03","unit":"-","category":"-"},{"hospName":"목동병원","itemName":"초음파검사료(진단초음파)/두경부-안 초음파/안구","price":154000,"ediCode":"EB4110001","date":"2025-09-03","unit":"-","category":"-"},{"hospName":"목동병원","itemName":"초음파검사료(진단초음파)/심장-경흉부 심초음파/단순","price":214000,"ediCode":"EB4310000","date":"2025-09-03","unit":"-","category":"-"},{"hospName":"목동병원","itemName":"자기공명영상진단료(MRI-기본검사)/근골격계-관절외 하지/일반","price":786000,"ediCode":"HE1230000","date":"2025-09-03","unit":"-","category":"-"},{"hospName":"목동병원","itemName":"초음파 검사료(유도 초음파)/유도초음파/Ⅰ","price":316000,"ediCode":"EB5610000","date":"2025-09-03","unit":"-","category":"-"},{"hospName":"목동병원","itemName":"자기공명영상진단료(MRI-기본검사)/복부-복부/일반","price":786000,"ediCode":"HE1270001","date":"2025-09-03","unit":"-","category":"-"},{"hospName":"목동병원","itemName":"초음파 검사료(유도 초음파)/수술 중 초음파","price":84000,"ediCode":"EZ9850000","date":"2025-09-03","unit":"-","category":"-"},{"hospName":"목동병원","itemName":"초음파검사료(진단초음파)/혈관-사지혈관 도플러 초음파/상지-동맥","price":164000,"ediCode":"EB4840000","date":"2025-09-03","unit":"-","category":"-"},{"hospName":"목동병원","itemName":"치료재료/재조합골형성단백질(RHBMP-2) 함유 골이식재/INFUSE RHBMP-2 BONE GRAFT","price":2340000,"ediCode":"BC0301AW","date":"2025-10-27","unit":"-","category":"-"},{"hospName":"목동병원","itemName":"이학요법료/FIMS(Functional Intramuscular Stimulation)","price":85200,"ediCode":"MZ0010000","date":"2025-09-03","unit":"-","category":"-"},{"hospName":"목동병원","itemName":"치과 처치· 수술료/광중합형 복합레진 충전/우식-2면","price":248600,"ediCode":"U02400000","date":"2025-09-03","unit":"-","category":"-"},{"hospName":"목동병원","itemName":"기능 검사료(신경계 기능검사)/증상 및 행동 평가척도/기타[이화방어기제검사]","price":15300,"ediCode":"FY7370000","date":"2025-09-03","unit":"-","category":"-"},{"hospName":"목동병원","itemName":"기능 검사료(호흡기 기능검사)/후각기능(인지 및 역치)검사","price":50000,"ediCode":"FZ6710000","date":"2025-09-03","unit":"-","category":"-"},{"hospName":"목동병원","itemName":"초음파검사료(진단초음파)/두경부-경부 초음파/갑상선·부갑상선 제외한 경부","price":191000,"ediCode":"EB4150000","date":"2025-09-03","unit":"-","category":"-"},{"hospName":"목동병원","itemName":"기능 검사료(신경계 기능검사)/정량적감각기능검사/진동역치","price":32700,"ediCode":"FY8810000","date":"2025-09-03","unit":"-","category":"-"},{"hospName":"목동병원","itemName":"치과의 보철료/치과임플란트(1치당)/Zirconia","price":3000000,"ediCode":"UB0010051","date":"2025-11-14","unit":"-","category":"-"},{"hospName":"목동병원","itemName":"기능 검사료(알레르기 검사)/경구 음식물유발시험과 경구 약물유발시험검사","price":279700,"ediCode":"EZ8480000","date":"2025-09-03","unit":"-","category":"-"},{"hospName":"목동병원","itemName":"기능 검사료(신경계 기능검사)/언어전반진단검사","price":126000,"ediCode":"FZ6890000","date":"2025-09-03","unit":"-","category":"-"},{"hospName":"목동병원","itemName":"초음파검사료(기본초음파)/단순초음파/Ⅱ","price":87000,"ediCode":"EB4020000","date":"2025-09-03","unit":"-","category":"-"},{"hospName":"목동병원","itemName":"초음파 검사료(유도 초음파)/유도초음파/Ⅰ","price":295000,"ediCode":"EB5610000","date":"2025-09-03","unit":"-","category":"-"},{"hospName":"목동병원","itemName":"치료재료/척추경막외 유착방지제/하이배리(HIBARRY)","price":217500,"ediCode":"BF0101VT","date":"2025-09-03","unit":"-","category":"-"},{"hospName":"목동병원","itemName":"처치 및 수술료(기타)/로봇 보조 수술 [시술시 소요재료 포함]-다빈치 기기/갑상선악성종양근치수술(갑상선암)","price":10000000,"ediCode":"QZ9610002","date":"2025-09-03","unit":"-","category":"-"},{"hospName":"목동병원","itemName":"기능 검사료(호흡기 기능검사)/후각기능(인지 및 역치)검사","price":49100,"ediCode":"FZ6710000","date":"2025-09-03","unit":"-","category":"-"},{"hospName":"목동병원","itemName":"치과 처치· 수술료/광중합형 복합레진 충전/우식-3면 이상","price":240000,"ediCode":"U02410000","date":"2025-09-03","unit":"-","category":"-"},{"hospName":"목동병원","itemName":"자기공명영상진단료(MRI-기본검사)/근골격계-고관절/조영제 주입 전·후 촬영 판독","price":819000,"ediCode":"HE2180000","date":"2025-09-03","unit":"-","category":"-"},{"hospName":"목동병원","itemName":"초음파검사료(진단초음파)/근골격, 연부-관절 초음파/주관절","price":105000,"ediCode":"EB4630000","date":"2025-09-03","unit":"-","category":"-"},{"hospName":"목동병원","itemName":"초음파 검사료(유도 초음파)/유도초음파/Ⅰ","price":211000,"ediCode":"EB5610000","date":"2025-09-03","unit":"-","category":"-"},{"hospName":"목동병원","itemName":"이학요법료/체외자기장 요실금치료[1일당]","price":31700,"ediCode":"MX0330000","date":"2025-09-03","unit":"-","category":"-"},{"hospName":"목동병원","itemName":"초음파 검사료(유도 초음파)/진공보조 유방 생검시 유도 초음파","price":1315000,"ediCode":"EZ9870000","date":"2025-09-03","unit":"-","category":"-"},{"hospName":"목동병원","itemName":"기능 검사료(평형 및 청각 기능검사)/비디오전기안진검사","price":50300,"ediCode":"FZ7330000","date":"2025-09-03","unit":"-","category":"-"},{"hospName":"목동병원","itemName":"자기공명영상진단료(MRI-기본검사)/혈관-흉부혈관/일반","price":822000,"ediCode":"HE1370001","date":"2025-09-03","unit":"-","category":"-"},{"hospName":"목동병원","itemName":"초음파검사료(기본초음파)/단순초음파/Ⅱ","price":158000,"ediCode":"EB4020000","date":"2025-09-03","unit":"-","category":"-"},{"hospName":"목동병원","itemName":"초음파검사료(진단초음파)/복부-복부 초음파/소장·대장","price":249000,"ediCode":"EB4440001","date":"2025-09-03","unit":"-","category":"-"},{"hospName":"목동병원","itemName":"이학요법료/비침습적 무통증 신호요법","price":112000,"ediCode":"MZ0120000","date":"2025-09-03","unit":"-","category":"-"},{"hospName":"목동병원","itemName":"처치 및 수술료(순환기)/고주파정맥내막폐쇄술[유도료 포함]/교통정맥결찰술을 동반하지 않은 경우","price":1000000,"ediCode":"OY2020000","date":"2025-09-03","unit":"-","category":"-"},{"hospName":"목동병원","itemName":"초음파검사료(진단초음파)/근골격, 연부-연부조직 초음파/정밀","price":178000,"ediCode":"EB4710000","date":"2025-10-22","unit":"-","category":"-"},{"hospName":"목동병원","itemName":"기능 검사료(외피, 근골 기능 검사)/동적 족저압측정","price":158400,"ediCode":"EZ7770000","date":"2025-09-03","unit":"-","category":"-"},{"hospName":"목동병원","itemName":"처치 및 수술료(근골)/체외충격파치료[근골격계질환]","price":64500,"ediCode":"SZ0840000","date":"2025-09-03","unit":"-","category":"-"},{"hospName":"목동병원","itemName":"치료재료/조절성 인공수정체/테크니스 퓨어SEE 토릭","price":1987700,"ediCode":"BI0213LN","date":"2025-09-03","unit":"-","category":"-"},{"hospName":"목동병원","itemName":"초음파검사료(진단초음파)/근골격, 연부-관절 초음파/슬관절","price":105000,"ediCode":"EB4640000","date":"2025-09-03","unit":"-","category":"-"},{"hospName":"목동병원","itemName":"치료재료/내시경 초음파를 이용한 세침흡인술용/VIZISHOT","price":319000,"ediCode":"BM0004LV","date":"2025-09-03","unit":"-","category":"-"},{"hospName":"목동병원","itemName":"초음파 검사료(유도 초음파)/유도초음파/Ⅱ","price":97000,"ediCode":"EB5620000","date":"2025-09-03","unit":"-","category":"-"},{"hospName":"목동병원","itemName":"치료재료/척추경막외 유착방지제/GUARDIX-SP PLUS(가딕스-SP PLUS),BARRIX(배릭스)","price":261000,"ediCode":"BM2103JO","date":"2025-09-03","unit":"-","category":"-"},{"hospName":"목동병원","itemName":"치료재료/척추경막외 유착방지제/PRECOAT","price":217500,"ediCode":"BF0100QF","date":"2025-09-03","unit":"-","category":"-"},{"hospName":"목동병원","itemName":"치료재료/동종진피(IMPLANT용-유방재건술용 제외)/CGDERM IMPLANT","price":67400,"ediCode":"BTS01013","date":"2025-10-22","unit":"-","category":"-"},{"hospName":"목동병원","itemName":"치료재료/재조합골형성단백질(RHBMP-2) 함유 골이식재/NOVOSIS","price":1417000,"ediCode":"BC0301QT","date":"2025-10-27","unit":"-","category":"-"},{"hospName":"목동병원","itemName":"치과 처치· 수술료/자가치아 이식술","price":551000,"ediCode":"UZ0820000","date":"2025-09-03","unit":"-","category":"-"},{"hospName":"목동병원","itemName":"기능 검사료(신경계 기능검사)/발음 및 발성검사","price":26200,"ediCode":"FZ6880000","date":"2025-09-03","unit":"-","category":"-"},{"hospName":"목동병원","itemName":"초음파 검사료(유도 초음파)/유도초음파/Ⅰ","price":211000,"ediCode":"EB5610000","date":"2025-09-03","unit":"-","category":"-"},{"hospName":"목동병원","itemName":"기능 검사료 (치아검사)/인상채득 및 모형제작 [1악당]","price":18000,"ediCode":"EX9340000","date":"2025-09-03","unit":"-","category":"-"},{"hospName":"목동병원","itemName":"자기공명영상진단료(MRI-기본검사)/두경부-부비동/일반","price":822000,"ediCode":"HE1040001","date":"2025-09-03","unit":"-","category":"-"},{"hospName":"목동병원","itemName":"초음파검사료(기본초음파)/단순초음파/Ⅱ","price":37000,"ediCode":"EB4020000","date":"2025-09-03","unit":"-","category":"-"},{"hospName":"목동병원","itemName":"치료재료/척추경막외 유착방지제/INTERBLOCK, GUARDIANWRAP PLUS","price":478500,"ediCode":"BF0100VD","date":"2025-10-27","unit":"-","category":"-"},{"hospName":"목동병원","itemName":"초음파검사료(진단초음파)/임산부 초음파/제2,3삼분기 -일반","price":107000,"ediCode":"EB5150000","date":"2025-09-03","unit":"-","category":"-"},{"hospName":"목동병원","itemName":"기능 검사료(평형 및 청각 기능검사)/비디오전기안진검사","price":30600,"ediCode":"FZ7330000","date":"2025-09-03","unit":"-","category":"-"},{"hospName":"목동병원","itemName":"초음파검사료(기본초음파)/단순초음파/Ⅰ","price":22000,"ediCode":"EB4010000","date":"2025-09-03","unit":"-","category":"-"},{"hospName":"목동병원","itemName":"초음파 검사료(유도 초음파)/유도초음파/Ⅱ","price":105000,"ediCode":"EB5620000","date":"2025-09-03","unit":"-","category":"-"},{"hospName":"목동병원","itemName":"병리검사료/세포병리검사/액상세포검사-자궁질 세포병리검사","price":104200,"ediCode":"3Z2102202","date":"2025-09-03","unit":"-","category":"-"},{"hospName":"목동병원","itemName":"치과 처치· 수술료/인레이(Inlay) 및 온레이(Onlay) 간접충전(금 등을 사용한 충전치료)-인레이/도재-세라믹","price":242000,"ediCode":"UZ0040013","date":"2025-09-03","unit":"-","category":"-"},{"hospName":"목동병원","itemName":"정신요법료/광치료","price":19700,"ediCode":"NZ0010000","date":"2025-09-03","unit":"-","category":"-"},{"hospName":"목동병원","itemName":"기능 검사료(소화기 기능 검사)/간섬유화검사","price":71400,"ediCode":"EZ8290000","date":"2025-09-03","unit":"-","category":"-"},{"hospName":"목동병원","itemName":"병리검사료/사람유전자 분자병리검사/비유전성 유전자검사-메틸화특이중합효소연쇄반응","price":280500,"ediCode":"CZ5840000","date":"2025-09-03","unit":"-","category":"-"},{"hospName":"목동병원","itemName":"치료재료/조절성 인공수정체/ACRYSOF IQ PANOPTIX PRESBYOPIA-CORRECTING IOL","price":2457000,"ediCode":"BI0208EB","date":"2025-09-03","unit":"-","category":"-"},{"hospName":"목동병원","itemName":"기능 검사료(신경계 기능검사)/주의력검사","price":47000,"ediCode":"FZ6900000","date":"2025-09-03","unit":"-","category":"-"},{"hospName":"목동병원","itemName":"기능 검사료(신경계 기능검사)/주의력검사","price":78600,"ediCode":"FZ6900000","date":"2025-09-03","unit":"-","category":"-"},{"hospName":"목동병원","itemName":"치과의 보철료/크라운/PFG","price":404000,"ediCode":"UW608F320","date":"2025-09-03","unit":"-","category":"-"},{"hospName":"목동병원","itemName":"기능 검사료(신경계 기능검사)/덴버발달검사","price":32700,"ediCode":"FZ6940000","date":"2025-09-03","unit":"-","category":"-"},{"hospName":"목동병원","itemName":"처치 및 수술료(보조생식술)/배아 이식[초음파유도료 포함] /자궁경관을 통한 이식","price":222900,"ediCode":"RZ6450001","date":"2025-09-03","unit":"-","category":"-"},{"hospName":"목동병원","itemName":"치료재료/척추경막외 유착방지제/GUARDIX-SP PLUS(가딕스-SP PLUS),BARRIX(배릭스)","price":522000,"ediCode":"BM2103JO","date":"2025-09-03","unit":"-","category":"-"},{"hospName":"목동병원","itemName":"초음파검사료(기본초음파)/단순초음파/Ⅱ","price":33000,"ediCode":"EB4020000","date":"2025-09-03","unit":"-","category":"-"},{"hospName":"목동병원","itemName":"예방접종료/수막구균/멘비오","price":130000,"ediCode":"3Z5200801","date":"2025-09-03","unit":"-","category":"-"},{"hospName":"목동병원","itemName":"초음파 검사료(유도 초음파)/유도초음파/Ⅱ","price":184000,"ediCode":"EB5620000","date":"2025-09-03","unit":"-","category":"-"},{"hospName":"목동병원","itemName":"초음파검사료(진단초음파)/신경-말초신경 초음파/편측","price":246000,"ediCode":"EB5030000","date":"2025-09-03","unit":"-","category":"-"},{"hospName":"목동병원","itemName":"기능 검사료(신경계 기능검사)/덴버발달검사","price":2800,"ediCode":"FZ6940000","date":"2025-09-03","unit":"-","category":"-"},{"hospName":"목동병원","itemName":"이학요법료/증식치료/척추부위","price":29600,"ediCode":"MY1430000","date":"2025-09-03","unit":"-","category":"-"},{"hospName":"목동병원","itemName":"이학요법료/체외자기장 요실금치료[1일당]","price":30600,"ediCode":"MX0330000","date":"2025-09-03","unit":"-","category":"-"},{"hospName":"목동병원","itemName":"처치 및 수술료(근골)/추간판내 고주파 열치료술","price":2495200,"ediCode":"SZ0830000","date":"2025-09-03","unit":"-","category":"-"},{"hospName":"목동병원","itemName":"기능 검사료(신경계 기능검사)/증상 및 행동 평가척도/기타[한국판성격평가척도(KPAI)]","price":71100,"ediCode":"FY7390000","date":"2025-09-03","unit":"-","category":"-"},{"hospName":"목동병원","itemName":"예방접종료/A형간염/박타프리필드시린지 1.0ml","price":53000,"ediCode":"3Z5202008","date":"2025-09-03","unit":"-","category":"-"},{"hospName":"목동병원","itemName":"예방접종료/사람유두종바이러스 감염증(HPV 백신)/가다실9프리필드시린지","price":210000,"ediCode":"3Z5201003","date":"2025-09-03","unit":"-","category":"-"},{"hospName":"목동병원","itemName":"치료재료/혈관내영상카테타/REFINITY ST ROTATIONAL IVUS CATHETER","price":1748500,"ediCode":"BJ4506JT","date":"2025-09-03","unit":"-","category":"-"},{"hospName":"목동병원","itemName":"검체검사료/안드로스테네디온","price":116900,"ediCode":"CZ1960000","date":"2025-09-03","unit":"-","category":"-"},{"hospName":"목동병원","itemName":"처치 및 수술료(코)/비밸브재건술","price":510000,"ediCode":"OZ1110000","date":"2025-09-03","unit":"-","category":"-"},{"hospName":"목동병원","itemName":"처치 및 수술료(기타)/로봇 보조 수술 [시술시 소요재료 포함]-다빈치 기기/갑상선악성종양근치수술(갑상선암)","price":9000000,"ediCode":"QZ9610002","date":"2025-09-03","unit":"-","category":"-"},{"hospName":"목동병원","itemName":"자기공명영상진단료(MRI-기본검사)/전신/일반","price":1201000,"ediCode":"HE1410001","date":"2025-09-03","unit":"-","category":"-"},{"hospName":"목동병원","itemName":"자기공명영상진단료(MRI-기본검사)/척추-흉추/일반","price":786000,"ediCode":"HE1100000","date":"2025-09-03","unit":"-","category":"-"},{"hospName":"목동병원","itemName":"초음파 검사료(유도 초음파)/유도초음파/Ⅱ","price":77000,"ediCode":"EB5620000","date":"2025-09-03","unit":"-","category":"-"},{"hospName":"목동병원","itemName":"기능 검사료(신경계 기능검사)/초음파를 활용한 뇌혈류 기능검사","price":88000,"ediCode":"FZ7140000","date":"2025-09-03","unit":"-","category":"-"},{"hospName":"목동병원","itemName":"처치 및 수술료(순환기)/시아노아크릴레이트를 이용한 복재정맥 폐색술[유도료 포함]","price":1000000,"ediCode":"OZ3030000","date":"2025-09-03","unit":"-","category":"-"},{"hospName":"목동병원","itemName":"기능 검사료(순환기 기능 검사)/동맥경화도검사(맥파전달속도측정)","price":80900,"ediCode":"EZ8680000","date":"2025-09-03","unit":"-","category":"-"},{"hospName":"목동병원","itemName":"치료재료/척추경막외 유착방지제/디베리아(DBARRIA)","price":710500,"ediCode":"BF0100QV","date":"2025-09-03","unit":"-","category":"-"},{"hospName":"목동병원","itemName":"초음파 검사료(유도 초음파)/유도초음파/Ⅰ","price":105000,"ediCode":"EB5610000","date":"2025-09-03","unit":"-","category":"-"},{"hospName":"목동병원","itemName":"내시경, 천자 및 생검료 /진정내시경환자관리료 /Ⅳ","price":139000,"ediCode":"EA0040000","date":"2025-09-03","unit":"-","category":"-"},{"hospName":"목동병원","itemName":"제증명수수료/진단서/일반","price":20000,"ediCode":"PDZ010000","date":"2025-09-03","unit":"-","category":"-"},{"hospName":"목동병원","itemName":"이학요법료/전산화 인지재활치료[주의·기억]","price":60000,"ediCode":"MZ0090000","date":"2025-09-03","unit":"-","category":"-"},{"hospName":"목동병원","itemName":"기능 검사료(신경계 기능검사)/자율신경계이상검사/기립성혈압검사","price":35000,"ediCode":"FY8910000","date":"2025-09-03","unit":"-","category":"-"},{"hospName":"목동병원","itemName":"처치 및 수술료(코)/비밸브재건술","price":255000,"ediCode":"OZ1110000","date":"2025-09-03","unit":"-","category":"-"},{"hospName":"목동병원","itemName":"제증명수수료/진료기록영상/CD","price":10000,"ediCode":"PDZ110004","date":"2025-09-03","unit":"-","category":"-"},{"hospName":"목동병원","itemName":"초음파 검사료(유도 초음파)/유도초음파/Ⅱ","price":184000,"ediCode":"EB5620000","date":"2025-09-03","unit":"-","category":"-"},{"hospName":"목동병원","itemName":"초음파검사료(진단초음파)/혈관-사지혈관 도플러 초음파/하지 정맥류","price":216000,"ediCode":"EB4890000","date":"2025-09-03","unit":"-","category":"-"},{"hospName":"목동병원","itemName":"제증명수수료/제증명서 사본","price":1000,"ediCode":"PDZ160000","date":"2025-09-03","unit":"-","category":"-"},{"hospName":"목동병원","itemName":"기능 검사료(알레르기 검사)/경구 음식물유발시험과 경구 약물유발시험검사","price":167200,"ediCode":"EZ8480000","date":"2025-09-03","unit":"-","category":"-"},{"hospName":"목동병원","itemName":"기능 검사료(외피, 근골 기능 검사)/동적 족저압측정","price":54700,"ediCode":"EZ7770000","date":"2025-09-03","unit":"-","category":"-"},{"hospName":"목동병원","itemName":"치과의 보철료/크라운/Zirconia","price":463000,"ediCode":"UW609F350","date":"2025-09-03","unit":"-","category":"-"},{"hospName":"목동병원","itemName":"처치 및 수술료(근골)/체외충격파치료[근골격계질환]","price":104000,"ediCode":"SZ0840000","date":"2025-09-03","unit":"-","category":"-"},{"hospName":"목동병원","itemName":"치과의 보철료/치과임플란트(1치당)/Zirconia","price":2600000,"ediCode":"UB0010051","date":"2025-11-14","unit":"-","category":"-"},{"hospName":"목동병원","itemName":"초음파 검사료(유도 초음파)/유도초음파/Ⅱ","price":202000,"ediCode":"EB5620000","date":"2025-09-03","unit":"-","category":"-"},{"hospName":"목동병원","itemName":"이학요법료/체외자기장 요실금치료[1일당]","price":16400,"ediCode":"MX0330000","date":"2025-09-03","unit":"-","category":"-"},{"hospName":"목동병원","itemName":"초음파 검사료(특수 초음파)/내시경초음파","price":861000,"ediCode":"EZ9920000","date":"2025-09-03","unit":"-","category":"-"},{"hospName":"목동병원","itemName":"기능 검사료(신경계 기능검사)/수면리듬양상검사","price":47800,"ediCode":"FZ7000000","date":"2025-09-03","unit":"-","category":"-"},{"hospName":"목동병원","itemName":"치료재료/기관지내시경초음파 가이드시스 KIT/GUIDE SHEATH KIT 2","price":333500,"ediCode":"BM0012LV","date":"2025-10-27","unit":"-","category":"-"},{"hospName":"목동병원","itemName":"자기공명영상진단료(MRI-기본검사)/혈관-사지혈관/조영제 주입 전·후 촬영 판독","price":819000,"ediCode":"HE2390000","date":"2025-09-03","unit":"-","category":"-"},{"hospName":"목동병원","itemName":"기능 검사료(신경계 기능검사)/언어전반진단검사","price":139800,"ediCode":"FZ6890000","date":"2025-09-03","unit":"-","category":"-"},{"hospName":"목동병원","itemName":"초음파 검사료(특수 초음파)/내시경초음파","price":319000,"ediCode":"EZ9920000","date":"2025-09-03","unit":"-","category":"-"},{"hospName":"목동병원","itemName":"치과의 보철료/크라운/PFM","price":290000,"ediCode":"UW608F310","date":"2025-09-03","unit":"-","category":"-"},{"hospName":"목동병원","itemName":"초음파검사료(진단초음파)/심장-경흉부 심초음파/일반","price":258000,"ediCode":"EB4320000","date":"2025-09-03","unit":"-","category":"-"},{"hospName":"목동병원","itemName":"치료재료/조절성 인공수정체/TECNIS TORIC 1-PIECE INTRAOCULAR LENS(IOL), TECNIS TORIC II 1-PIECE IOL","price":970200,"ediCode":"BI0204LN","date":"2025-09-03","unit":"-","category":"-"},{"hospName":"목동병원","itemName":"초음파 검사료(유도 초음파)/유도초음파/Ⅱ","price":265000,"ediCode":"EB5620000","date":"2025-09-03","unit":"-","category":"-"},{"hospName":"목동병원","itemName":"처치 및 수술료(비뇨기)/이식형 결찰사를 이용한 전립선 결찰","price":9000000,"ediCode":"RZ5150000","date":"2025-09-03","unit":"-","category":"-"},{"hospName":"목동병원","itemName":"초음파검사료(진단초음파)/진단초음파/흉부-유방·액와부 초음파 /정밀","price":208000,"ediCode":"EB4230000","date":"2025-09-03","unit":"-","category":"-"},{"hospName":"목동병원","itemName":"초음파검사료(진단초음파)/복부-복부 초음파/충수","price":249000,"ediCode":"EB4430001","date":"2025-09-03","unit":"-","category":"-"},{"hospName":"목동병원","itemName":"치료재료/척추경막외 유착방지제/X-AD","price":232000,"ediCode":"BF0100BK","date":"2025-09-03","unit":"-","category":"-"},{"hospName":"목동병원","itemName":"초음파 검사료(유도 초음파)/수술 중 초음파","price":137000,"ediCode":"EZ9850000","date":"2025-09-03","unit":"-","category":"-"},{"hospName":"목동병원","itemName":"초음파검사료(진단초음파)/혈관-사지혈관 도플러 초음파/상지-정맥","price":147000,"ediCode":"EB4850000","date":"2025-09-03","unit":"-","category":"-"},{"hospName":"목동병원","itemName":"초음파검사료(진단초음파)/진단초음파/흉부-유방·액와부 초음파 /일반","price":208000,"ediCode":"EB4210000","date":"2025-09-03","unit":"-","category":"-"},{"hospName":"목동병원","itemName":"기능 검사료(신경계 기능검사)/언어전반진단검사","price":55400,"ediCode":"FZ6890000","date":"2025-09-03","unit":"-","category":"-"},{"hospName":"목동병원","itemName":"기능 검사료(호흡기 기능검사)/후각기능(인지 및 역치)검사","price":18700,"ediCode":"FZ6710000","date":"2025-09-03","unit":"-","category":"-"},{"hospName":"목동병원","itemName":"자기공명영상진단료(MRI-기본검사)/척추-요천추/일반","price":786000,"ediCode":"HE1110000","date":"2025-09-03","unit":"-","category":"-"},{"hospName":"목동병원","itemName":"초음파검사료(진단초음파)/혈관-사지혈관 도플러 초음파/상지-동맥","price":240000,"ediCode":"EB4840000","date":"2025-09-03","unit":"-","category":"-"},{"hospName":"목동병원","itemName":"초음파 검사료(유도 초음파)/유도초음파/Ⅱ","price":265000,"ediCode":"EB5620000","date":"2025-09-03","unit":"-","category":"-"},{"hospName":"목동병원","itemName":"초음파검사료(진단초음파)/근골격, 연부-관절 초음파/손가락","price":84000,"ediCode":"EB4610000","date":"2025-09-03","unit":"-","category":"-"},{"hospName":"목동병원","itemName":"기능 검사료(알레르기 검사)/주사제 약물 유발시험","price":69200,"ediCode":"EZ8470000","date":"2025-09-03","unit":"-","category":"-"},{"hospName":"목동병원","itemName":"검체검사료/인플루엔자 A·B 바이러스항원검사[현장검사]","price":46400,"ediCode":"CZ3940000","date":"2025-09-03","unit":"-","category":"-"},{"hospName":"목동병원","itemName":"치료재료/척추경막외 유착방지제/디베리아(DBARRIA)","price":565500,"ediCode":"BF0100QV","date":"2025-09-03","unit":"-","category":"-"},{"hospName":"목동병원","itemName":"기능 검사료(평형 및 청각 기능검사)/동적체평형검사","price":71100,"ediCode":"FZ7310000","date":"2025-09-03","unit":"-","category":"-"},{"hospName":"목동병원","itemName":"치료재료/혈관내영상카테타/EAGLE EYE IVUS CATHETER","price":1659000,"ediCode":"BJ4504JT","date":"2025-09-03","unit":"-","category":"-"},{"hospName":"목동병원","itemName":"초음파검사료(진단초음파)/임산부 초음파/제2,3삼분기 -일반","price":97000,"ediCode":"EB5150000","date":"2025-09-03","unit":"-","category":"-"},{"hospName":"목동병원","itemName":"치료재료/조절성 인공수정체/TECNIS SYMFONY EXTENDED RANGE OF VISION IOL, TECNIS SYMFONY PLUS EXTENDED RANGE OF VISION IOL","price":2600000,"ediCode":"BI0205LN","date":"2025-09-03","unit":"-","category":"-"},{"hospName":"목동병원","itemName":"자기공명영상진단료(MRI-특수검사)/영화 [기본검사 및 3차원자기공명영상 포함]","price":650000,"ediCode":"HF1040000","date":"2025-09-03","unit":"-","category":"-"},{"hospName":"목동병원","itemName":"자기공명영상진단료(MRI-기본검사)/근골격계-천장골관절/조영제 주입 전·후 촬영 판독","price":819000,"ediCode":"HE2190000","date":"2025-09-03","unit":"-","category":"-"},{"hospName":"목동병원","itemName":"치과의 보철료/크라운/PFM","price":390000,"ediCode":"UW608F310","date":"2025-09-03","unit":"-","category":"-"},{"hospName":"목동병원","itemName":"처치 및 수술료(기타)/로봇 보조 수술 [시술시 소요재료 포함]-다빈치 기기/갑상선악성종양근치수술(갑상선암)","price":7000000,"ediCode":"QZ9610002","date":"2025-09-03","unit":"-","category":"-"},{"hospName":"목동병원","itemName":"자기공명영상진단료(MRI-기본검사)/근골격계-관절외 상지/조영제 주입 전·후 촬영 판독","price":819000,"ediCode":"HE2220000","date":"2025-09-03","unit":"-","category":"-"},{"hospName":"목동병원","itemName":"초음파 검사료(특수 초음파)/내시경초음파","price":921000,"ediCode":"EZ9920000","date":"2025-09-03","unit":"-","category":"-"},{"hospName":"목동병원","itemName":"초음파검사료(진단초음파)/복부-여성생식기 초음파/일반-자궁내 생리식염수를 주입하여 검사","price":129000,"ediCode":"EB4560001","date":"2025-09-03","unit":"-","category":"-"},{"hospName":"목동병원","itemName":"치료재료/재조합골형성단백질(RHBMP-2) 함유 골이식재/INFUSE RHBMP-2 BONE GRAFT","price":7920000,"ediCode":"BC0301AW","date":"2025-10-27","unit":"-","category":"-"},{"hospName":"목동병원","itemName":"치과 처치· 수술료/인레이(Inlay) 및 온레이(Onlay) 간접충전(금 등을 사용한 충전치료)-인레이/레진","price":297000,"ediCode":"UZ0040012","date":"2025-09-03","unit":"-","category":"-"},{"hospName":"목동병원","itemName":"초음파 검사료(유도 초음파)/유도초음파/Ⅱ","price":105000,"ediCode":"EB5620000","date":"2025-09-03","unit":"-","category":"-"},{"hospName":"목동병원","itemName":"기능 검사료(평형 및 청각 기능검사)/비디오전기안진검사","price":30600,"ediCode":"FZ7330000","date":"2025-09-03","unit":"-","category":"-"},{"hospName":"목동병원","itemName":"이학요법료/언어치료","price":66000,"ediCode":"MZ0060000","date":"2025-09-03","unit":"-","category":"-"},{"hospName":"목동병원","itemName":"처치 및 수술료(보조생식술)/배아 동결·보존","price":521000,"ediCode":"RZ6470000","date":"2025-09-03","unit":"-","category":"-"},{"hospName":"목동병원","itemName":"제증명수수료/병무용진단서","price":20000,"ediCode":"PDZ080000","date":"2025-09-03","unit":"-","category":"-"},{"hospName":"목동병원","itemName":"초음파검사료(진단초음파)/혈관-사지혈관 도플러 초음파/하지-동맥","price":240000,"ediCode":"EB4870000","date":"2025-09-03","unit":"-","category":"-"},{"hospName":"목동병원","itemName":"처치 및 수술료(순환기)/레이저정맥폐쇄술[유도료 포함]","price":1310900,"ediCode":"OZ3040000","date":"2025-09-03","unit":"-","category":"-"},{"hospName":"목동병원","itemName":"치과의 보철료/크라운/Metal","price":220000,"ediCode":"UW607F310","date":"2025-09-03","unit":"-","category":"-"},{"hospName":"목동병원","itemName":"치과 처치· 수술료/광중합형 복합레진 충전/우식-1면","price":30000,"ediCode":"U02390000","date":"2025-09-03","unit":"-","category":"-"},{"hospName":"목동병원","itemName":"제증명수수료/향후진료비추정서/천만원 미만","price":50000,"ediCode":"PDZ140001","date":"2025-09-03","unit":"-","category":"-"},{"hospName":"목동병원","itemName":"초음파검사료(기본초음파)/단순초음파/Ⅱ","price":95000,"ediCode":"EB4020000","date":"2025-09-03","unit":"-","category":"-"},{"hospName":"목동병원","itemName":"제증명수수료/진단서/근로능력평가용","price":10000,"ediCode":"PDZ010002","date":"2025-09-03","unit":"-","category":"-"},{"hospName":"목동병원","itemName":"초음파 검사료(유도 초음파)/유도초음파/Ⅱ","price":250000,"ediCode":"EB5620000","date":"2025-09-03","unit":"-","category":"-"},{"hospName":"목동병원","itemName":"자기공명영상진단료(MRI-기본검사)/근골격계-발목관절/일반","price":786000,"ediCode":"HE1210000","date":"2025-09-03","unit":"-","category":"-"}]